{
  "type": "Feature",
  "properties": {
    "gn:admin1_code":"01",
    "gn:admin2_code":"2198131",
    "gn:asciiname":"Naivitabua Settlement",
    "gn:country_code":"FJ",
    "gn:dem":7,
    "gn:feature_class":"P",
    "gn:feature_code":"PPL",
    "gn:name":"Naivitabua Settlement",
    "gn:population":0,
    "gn:timezone":"Pacific/Fiji",
    "iso:country":"FJ",
    "name:fij_x_preferred":[
        "Naivitabua Settlement"
    ],
    "wof:name":"Naivitabua Settlement",
    "wof:placetype":"locality"
},
  "geometry": {"coordinates":[178.58768999999995,-17.83745],"type":"Point"}
}