{
  "type": "Feature",
  "properties": {
    "gn:admin1_code":"01",
    "gn:admin2_code":"2202182",
    "gn:asciiname":"Nabukavesi",
    "gn:country_code":"FJ",
    "gn:dem":13,
    "gn:feature_class":"P",
    "gn:feature_code":"PPL",
    "gn:name":"Nabukavesi",
    "gn:population":0,
    "gn:timezone":"Pacific/Fiji",
    "iso:country":"FJ",
    "name:fij_x_preferred":[
        "Nabukavesi"
    ],
    "name:fij_x_variant":[
        "Nambukavesi"
    ],
    "wof:name":"Nabukavesi",
    "wof:placetype":"locality"
},
  "geometry": {"coordinates":[178.23887999999999,-18.1609],"type":"Point"}
}