{
  "type": "Feature",
  "properties": {
    "gn:admin1_code":"01",
    "gn:admin2_code":"2198131",
    "gn:asciiname":"Naigani",
    "gn:country_code":"FJ",
    "gn:dem":18,
    "gn:feature_class":"P",
    "gn:feature_code":"PPL",
    "gn:name":"Naigani",
    "gn:population":0,
    "gn:timezone":"Pacific/Fiji",
    "iso:country":"FJ",
    "name:fij_x_preferred":[
        "Naigani"
    ],
    "name:fij_x_variant":[
        "Naingani"
    ],
    "wof:name":"Naigani",
    "wof:placetype":"locality"
},
  "geometry": {"coordinates":[178.67211,-17.58318],"type":"Point"}
}