{
  "type": "Feature",
  "properties": {
    "gn:admin1_code":"01",
    "gn:admin2_code":"2198131",
    "gn:asciiname":"Draubuta",
    "gn:country_code":"FJ",
    "gn:dem":6,
    "gn:feature_class":"P",
    "gn:feature_code":"PPL",
    "gn:name":"Draubuta",
    "gn:population":0,
    "gn:timezone":"Pacific/Fiji",
    "iso:country":"FJ",
    "name:fij_x_preferred":[
        "Draubuta"
    ],
    "name:fij_x_variant":[
        "Ndraumbuta"
    ],
    "wof:name":"Draubuta",
    "wof:placetype":"locality"
},
  "geometry": {"coordinates":[178.58041,-18.07165],"type":"Point"}
}