{
  "type": "Feature",
  "properties": {
    "gn:admin1_code":"01",
    "gn:admin2_code":"2203150",
    "gn:asciiname":"Natuva",
    "gn:country_code":"FJ",
    "gn:dem":17,
    "gn:feature_class":"P",
    "gn:feature_code":"PPL",
    "gn:name":"Natuva",
    "gn:population":0,
    "gn:timezone":"Pacific/Fiji",
    "iso:country":"FJ",
    "name:fij_x_preferred":[
        "Natuva"
    ],
    "wof:name":"Natuva",
    "wof:placetype":"locality"
},
  "geometry": {"coordinates":[178.39445000000001,-17.85154],"type":"Point"}
}