{
  "type": "Feature",
  "properties": {
    "gn:admin1_code":"01",
    "gn:admin2_code":"2198131",
    "gn:asciiname":"Namuka",
    "gn:country_code":"FJ",
    "gn:dem":5,
    "gn:feature_class":"P",
    "gn:feature_code":"PPL",
    "gn:name":"Namuka",
    "gn:population":0,
    "gn:timezone":"Pacific/Fiji",
    "iso:country":"FJ",
    "name:ceb_x_preferred":[
        "Namuka"
    ],
    "name:fij_x_preferred":[
        "Namuka"
    ],
    "wof:name":"Namuka",
    "wof:placetype":"locality"
},
  "geometry": {"coordinates":[178.59520000000001,-17.97799999999999],"type":"Point"}
}