{
  "type": "Feature",
  "properties": {
    "gn:admin1_code":"2.0",
    "gn:admin2_code":"8617786.0",
    "gn:asciiname":"Waisomo",
    "gn:country_code":"FJ",
    "gn:dem":10,
    "gn:feature_class":"P",
    "gn:feature_code":"PPL",
    "gn:name":"Waisomo",
    "gn:population":0,
    "gn:timezone":"Pacific/Fiji",
    "iso:country":"FJ",
    "name:fij_x_preferred":[
        "Waisomo"
    ],
    "wof:name":"Waisomo",
    "wof:placetype":"locality"
},
  "geometry": {"coordinates":[178.47678999999999,-18.92273],"type":"Point"}
}