{
  "type": "Feature",
  "properties": {
    "gn:admin1_code":"5.0",
    "gn:admin2_code":"2201984.0",
    "gn:asciiname":"Vatukarasa",
    "gn:country_code":"FJ",
    "gn:dem":18,
    "gn:feature_class":"P",
    "gn:feature_code":"PPL",
    "gn:name":"Vatukarasa",
    "gn:population":0,
    "gn:timezone":"Pacific/Fiji",
    "iso:country":"FJ",
    "name:und_x_variant":[
        "Vatau Karasa",
        "Vatukarasa"
    ],
    "wof:name":"Vatukarasa",
    "wof:placetype":"locality"
},
  "geometry": {"coordinates":[177.6045,-18.18202],"type":"Point"}
}