{
  "type": "Feature",
  "properties": {
    "gn:admin1_code":"01",
    "gn:admin2_code":"2203150",
    "gn:asciiname":"Navutu",
    "gn:country_code":"FJ",
    "gn:dem":51,
    "gn:feature_class":"P",
    "gn:feature_code":"PPL",
    "gn:name":"Navutu",
    "gn:population":0,
    "gn:timezone":"Pacific/Fiji",
    "iso:country":"FJ",
    "name:fij_x_preferred":[
        "Navutu"
    ],
    "name:fij_x_variant":[
        "Navuto"
    ],
    "wof:name":"Navutu",
    "wof:placetype":"locality"
},
  "geometry": {"coordinates":[178.38266000000004,-17.90468],"type":"Point"}
}