{
  "type": "Feature",
  "properties": {
    "gn:admin1_code":"05",
    "gn:asciiname":"Natewa",
    "gn:country_code":"FJ",
    "gn:dem":118,
    "gn:feature_class":"P",
    "gn:feature_code":"PPL",
    "gn:name":"Natewa",
    "gn:population":0,
    "gn:timezone":"Pacific/Fiji",
    "iso:country":"FJ",
    "name:fij_x_preferred":[
        "Natewa"
    ],
    "wof:name":"Natewa",
    "wof:placetype":"locality"
},
  "geometry": {"coordinates":[177.66666999999995,-18.16667],"type":"Point"}
}