{
  "type": "Feature",
  "properties": {
    "gn:admin1_code":"05",
    "gn:asciiname":"Bukama",
    "gn:country_code":"FJ",
    "gn:dem":6,
    "gn:feature_class":"P",
    "gn:feature_code":"PPL",
    "gn:name":"Bukama",
    "gn:population":0,
    "gn:timezone":"Pacific/Fiji",
    "iso:country":"FJ",
    "name:eng_x_preferred":[
        "Bukama"
    ],
    "wof:name":"Bukama",
    "wof:placetype":"locality"
},
  "geometry": {"coordinates":[177.55337,-16.75976],"type":"Point"}
}