{
  "type": "Feature",
  "properties": {
    "gn:admin1_code":"05",
    "gn:asciiname":"Bukama",
    "gn:country_code":"FJ",
    "gn:dem":6,
    "gn:feature_class":"P",
    "gn:feature_code":"PPL",
    "gn:name":"Bukama",
    "gn:population":0,
    "gn:timezone":"Pacific/Fiji",
    "iso:country":"FJ",
    "name:ceb_x_preferred":[
        "Bukama"
    ],
    "name:deu_x_preferred":[
        "Bukama"
    ],
    "name:eng_x_preferred":[
        "Bukama"
    ],
    "name:fas_x_preferred":[
        "\u0628\u0648\u06a9\u0627\u0645\u0627"
    ],
    "name:fra_x_preferred":[
        "Bukama"
    ],
    "name:heb_x_preferred":[
        "\u05d1\u05d5\u05e7\u05de\u05d4"
    ],
    "name:hun_x_preferred":[
        "Bukama"
    ],
    "name:ita_x_preferred":[
        "Bukama"
    ],
    "name:pol_x_preferred":[
        "Bukama"
    ],
    "name:ron_x_preferred":[
        "Bukama"
    ],
    "name:swe_x_preferred":[
        "Bukama"
    ],
    "name:tgl_x_preferred":[
        "Bukama"
    ],
    "name:zho_x_preferred":[
        "\u5e03\u5361\u99ac"
    ],
    "wof:name":"Bukama",
    "wof:placetype":"locality"
},
  "geometry": {"coordinates":[177.55337,-16.75976],"type":"Point"}
}