{
  "type": "Feature",
  "properties": {
    "gn:admin1_code":"01",
    "gn:admin2_code":"2203150",
    "gn:asciiname":"Namatabitu Settlement",
    "gn:country_code":"FJ",
    "gn:dem":30,
    "gn:feature_class":"P",
    "gn:feature_code":"PPL",
    "gn:name":"Namatabitu Settlement",
    "gn:population":0,
    "gn:timezone":"Pacific/Fiji",
    "iso:country":"FJ",
    "name:fij_x_preferred":[
        "Namatabitu Settlement"
    ],
    "wof:name":"Namatabitu Settlement",
    "wof:placetype":"locality"
},
  "geometry": {"coordinates":[178.34929,-17.80624],"type":"Point"}
}