{
  "type": "Feature",
  "properties": {
    "gn:admin1_code":"03",
    "gn:admin2_code":"2203651",
    "gn:asciiname":"Kavula",
    "gn:country_code":"FJ",
    "gn:dem":108,
    "gn:feature_class":"P",
    "gn:feature_code":"PPL",
    "gn:name":"Kavula",
    "gn:population":0,
    "gn:timezone":"Pacific/Fiji",
    "iso:country":"FJ",
    "name:fij_x_preferred":[
        "Kavula"
    ],
    "wof:name":"Kavula",
    "wof:placetype":"locality"
},
  "geometry": {"coordinates":[178.74216000000001,-16.73838],"type":"Point"}
}