{
  "type": "Feature",
  "properties": {
    "gn:admin1_code":"03",
    "gn:admin2_code":"2197820",
    "gn:asciiname":"Naviavia",
    "gn:country_code":"FJ",
    "gn:dem":13,
    "gn:feature_class":"P",
    "gn:feature_code":"PPL",
    "gn:name":"Naviavia",
    "gn:population":0,
    "gn:timezone":"Pacific/Fiji",
    "iso:country":"FJ",
    "name:fij_x_preferred":[
        "Naviavia"
    ],
    "wof:name":"Naviavia",
    "wof:placetype":"locality"
},
  "geometry": {"coordinates":[179.09594999999999,-16.76487],"type":"Point"}
}