{
  "type": "Feature",
  "properties": {
    "gn:admin1_code":"05",
    "gn:asciiname":"Nandele",
    "gn:country_code":"FJ",
    "gn:dem":152,
    "gn:feature_class":"P",
    "gn:feature_code":"PPL",
    "gn:name":"Nandele",
    "gn:population":0,
    "gn:timezone":"Pacific/Fiji",
    "iso:country":"FJ",
    "name:fij_x_preferred":[
        "Nandele"
    ],
    "wof:name":"Nandele",
    "wof:placetype":"locality"
},
  "geometry": {"coordinates":[177.56666999999999,-17.73333],"type":"Point"}
}