{
  "type": "Feature",
  "properties": {
    "gn:admin1_code":"03",
    "gn:admin2_code":"2197820",
    "gn:asciiname":"Navarada Settlement",
    "gn:country_code":"FJ",
    "gn:dem":9,
    "gn:feature_class":"P",
    "gn:feature_code":"PPL",
    "gn:name":"Navarada Settlement",
    "gn:population":0,
    "gn:timezone":"Pacific/Fiji",
    "iso:country":"FJ",
    "name:fij_x_preferred":[
        "Navarada Settlement"
    ],
    "wof:name":"Navarada Settlement",
    "wof:placetype":"locality"
},
  "geometry": {"coordinates":[179.99133999999995,-16.80317],"type":"Point"}
}