{
  "type": "Feature",
  "properties": {
    "gn:admin1_code":"03",
    "gn:admin2_code":"2197820",
    "gn:asciiname":"Navatuosooso Settlement",
    "gn:country_code":"FJ",
    "gn:dem":98,
    "gn:feature_class":"P",
    "gn:feature_code":"PPL",
    "gn:name":"Navatuosooso Settlement",
    "gn:population":0,
    "gn:timezone":"Pacific/Fiji",
    "iso:country":"FJ",
    "name:fij_x_preferred":[
        "Navatuosooso Settlement"
    ],
    "wof:name":"Navatuosooso Settlement",
    "wof:placetype":"locality"
},
  "geometry": {"coordinates":[179.91353999999995,-16.9808],"type":"Point"}
}