{
  "type": "Feature",
  "properties": {
    "gn:admin1_code":"03",
    "gn:admin2_code":"2203651",
    "gn:asciiname":"Wailele Settlement",
    "gn:country_code":"FJ",
    "gn:dem":21,
    "gn:feature_class":"P",
    "gn:feature_code":"PPL",
    "gn:name":"Wailele Settlement",
    "gn:population":0,
    "gn:timezone":"Pacific/Fiji",
    "iso:country":"FJ",
    "name:fij_x_preferred":[
        "Wailele Settlement"
    ],
    "wof:name":"Wailele Settlement",
    "wof:placetype":"locality"
},
  "geometry": {"coordinates":[178.65937,-16.91689],"type":"Point"}
}