{
  "type": "Feature",
  "properties": {
    "gn:admin1_code":"05",
    "gn:admin2_code":"2198946",
    "gn:asciiname":"Navesi Settlement",
    "gn:country_code":"FJ",
    "gn:dem":124,
    "gn:feature_class":"P",
    "gn:feature_code":"PPL",
    "gn:name":"Navesi Settlement",
    "gn:population":0,
    "gn:timezone":"Pacific/Fiji",
    "iso:country":"FJ",
    "name:fij_x_preferred":[
        "Navesi Settlement"
    ],
    "wof:name":"Navesi Settlement",
    "wof:placetype":"locality"
},
  "geometry": {"coordinates":[178.27177,-17.51736],"type":"Point"}
}