{
  "type": "Feature",
  "properties": {
    "gn:admin1_code":"02",
    "gn:admin2_code":"2204318",
    "gn:asciiname":"Wakaya Settlement",
    "gn:country_code":"FJ",
    "gn:dem":1,
    "gn:feature_class":"P",
    "gn:feature_code":"PPL",
    "gn:name":"Wakaya Settlement",
    "gn:population":0,
    "gn:timezone":"Pacific/Fiji",
    "iso:country":"FJ",
    "name:fij_x_preferred":[
        "Wakaya Settlement"
    ],
    "wof:name":"Wakaya Settlement",
    "wof:placetype":"locality"
},
  "geometry": {"coordinates":[178.98438000000004,-17.59897999999999],"type":"Point"}
}