{
  "type": "Feature",
  "properties": {
    "gn:admin1_code":"03",
    "gn:admin2_code":"2203651",
    "gn:asciiname":"Natokalau",
    "gn:country_code":"FJ",
    "gn:dem":4,
    "gn:feature_class":"P",
    "gn:feature_code":"PPL",
    "gn:name":"Natokalau",
    "gn:population":0,
    "gn:timezone":"Pacific/Fiji",
    "iso:country":"FJ",
    "name:fij_x_preferred":[
        "Natokalau"
    ],
    "wof:name":"Natokalau",
    "wof:placetype":"locality"
},
  "geometry": {"coordinates":[179.05766,-16.9066],"type":"Point"}
}