{
  "type": "Feature",
  "properties": {
    "gn:admin1_code":"4.0",
    "gn:asciiname":"Uanheta",
    "gn:country_code":"FJ",
    "gn:dem":7,
    "gn:feature_class":"P",
    "gn:feature_code":"PPL",
    "gn:name":"Uanheta",
    "gn:population":0,
    "gn:timezone":"Pacific/Fiji",
    "iso:country":"FJ",
    "name:fij_x_preferred":[
        "Uanheta"
    ],
    "wof:name":"Uanheta",
    "wof:placetype":"locality"
},
  "geometry": {"coordinates":[177.10082,-12.52206],"type":"Point"}
}