{
  "type": "Feature",
  "properties": {
    "gn:admin1_code":"1.0",
    "gn:admin2_code":"2198876.0",
    "gn:asciiname":"Vunisei",
    "gn:country_code":"FJ",
    "gn:dem":8,
    "gn:feature_class":"P",
    "gn:feature_code":"PPL",
    "gn:name":"Vunisei",
    "gn:population":0,
    "gn:timezone":"Pacific/Fiji",
    "iso:country":"FJ",
    "name:und_x_variant":[
        "Vunisea",
        "Vunisei"
    ],
    "wof:name":"Vunisei",
    "wof:placetype":"locality"
},
  "geometry": {"coordinates":[178.55431999999999,-18.05425],"type":"Point"}
}