{
  "type": "Feature",
  "properties": {
    "gn:admin1_code":"05",
    "gn:admin2_code":"2198946",
    "gn:asciiname":"Burenikita Settlement",
    "gn:country_code":"FJ",
    "gn:dem":1,
    "gn:feature_class":"P",
    "gn:feature_code":"PPL",
    "gn:name":"Burenikita Settlement",
    "gn:population":0,
    "gn:timezone":"Pacific/Fiji",
    "iso:country":"FJ",
    "name:fij_x_preferred":[
        "Burenikita Settlement"
    ],
    "wof:name":"Burenikita Settlement",
    "wof:placetype":"locality"
},
  "geometry": {"coordinates":[178.37513000000001,-17.5403],"type":"Point"}
}