{
  "type": "Feature",
  "properties": {
    "gn:admin1_code":"5.0",
    "gn:admin2_code":"2198946.0",
    "gn:asciiname":"Vaileka",
    "gn:country_code":"FJ",
    "gn:dem":13,
    "gn:feature_class":"P",
    "gn:feature_code":"PPL",
    "gn:name":"Vaileka",
    "gn:population":0,
    "gn:timezone":"Pacific/Fiji",
    "iso:country":"FJ",
    "name:und_x_variant":[
        "Vailaka",
        "Vaileka"
    ],
    "wof:name":"Vaileka",
    "wof:placetype":"locality"
},
  "geometry": {"coordinates":[178.15329,-17.37894],"type":"Point"}
}