{
  "type": "Feature",
  "properties": {
    "gn:admin1_code":"01",
    "gn:asciiname":"Nakavika",
    "gn:country_code":"FJ",
    "gn:dem":127,
    "gn:feature_class":"P",
    "gn:feature_code":"PPL",
    "gn:name":"Nakavika",
    "gn:population":0,
    "gn:timezone":"Pacific/Fiji",
    "iso:country":"FJ",
    "wof:name":"Nakavika",
    "wof:placetype":"locality"
},
  "geometry": {"coordinates":[178.06846999999999,-18.06529],"type":"Point"}
}