{
  "type": "Feature",
  "properties": {
    "gn:admin1_code":"01",
    "gn:admin2_code":"2198131",
    "gn:asciiname":"Buitua Settlement",
    "gn:country_code":"FJ",
    "gn:dem":39,
    "gn:feature_class":"P",
    "gn:feature_code":"PPL",
    "gn:name":"Buitua Settlement",
    "gn:population":0,
    "gn:timezone":"Pacific/Fiji",
    "iso:country":"FJ",
    "name:fij_x_preferred":[
        "Buitua Settlement"
    ],
    "wof:name":"Buitua Settlement",
    "wof:placetype":"locality"
},
  "geometry": {"coordinates":[178.42317,-17.73422],"type":"Point"}
}