{
  "type": "Feature",
  "properties": {
    "gn:admin1_code":"00",
    "gn:asciiname":"Oinafa",
    "gn:country_code":"FJ",
    "gn:dem":7,
    "gn:feature_class":"P",
    "gn:feature_code":"PPL",
    "gn:name":"Oinafa",
    "gn:population":0,
    "gn:timezone":"Pacific/Fiji",
    "iso:country":"FJ",
    "name:ceb_x_preferred":[
        "Oinafa"
    ],
    "name:swe_x_preferred":[
        "Oinafa"
    ],
    "wof:name":"Oinafa",
    "wof:placetype":"locality"
},
  "geometry": {"coordinates":[177.12502000000001,-12.48883],"type":"Point"}
}