{
  "type": "Feature",
  "properties": {
    "gn:admin1_code":"02",
    "gn:admin2_code":"2204318",
    "gn:asciiname":"Naqeledamudamu Settlement",
    "gn:country_code":"FJ",
    "gn:dem":14,
    "gn:feature_class":"P",
    "gn:feature_code":"PPL",
    "gn:name":"Naqeledamudamu Settlement",
    "gn:population":0,
    "gn:timezone":"Pacific/Fiji",
    "iso:country":"FJ",
    "name:fij_x_preferred":[
        "Naqeledamudamu Settlement"
    ],
    "wof:name":"Naqeledamudamu Settlement",
    "wof:placetype":"locality"
},
  "geometry": {"coordinates":[178.77513000000005,-17.74355],"type":"Point"}
}