{
  "type": "Feature",
  "properties": {
    "gn:admin1_code":"02",
    "gn:admin2_code":"8617786",
    "gn:asciiname":"Namanusa",
    "gn:country_code":"FJ",
    "gn:dem":29,
    "gn:feature_class":"P",
    "gn:feature_code":"PPL",
    "gn:name":"Namanusa",
    "gn:population":0,
    "gn:timezone":"Pacific/Fiji",
    "iso:country":"FJ",
    "name:und_x_variant":[
        "Ravitaki",
        "Namanusa"
    ],
    "wof:name":"Namanusa",
    "wof:placetype":"locality"
},
  "geometry": {"coordinates":[178.12933999999996,-19.13268],"type":"Point"}
}