{
  "type": "Feature",
  "properties": {
    "gn:admin1_code":"05",
    "gn:admin2_code":"2198946",
    "gn:asciiname":"Saioko",
    "gn:country_code":"FJ",
    "gn:dem":25,
    "gn:feature_class":"P",
    "gn:feature_code":"PPL",
    "gn:name":"Saioko",
    "gn:population":0,
    "gn:timezone":"Pacific/Fiji",
    "iso:country":"FJ",
    "name:fij_x_preferred":[
        "Saioko"
    ],
    "wof:name":"Saioko",
    "wof:placetype":"locality"
},
  "geometry": {"coordinates":[178.37103000000005,-17.54107999999999],"type":"Point"}
}