{
  "type": "Feature",
  "properties": {
    "gn:admin1_code":"03",
    "gn:admin2_code":"2197820",
    "gn:asciiname":"Nayarailagi",
    "gn:country_code":"FJ",
    "gn:dem":23,
    "gn:feature_class":"P",
    "gn:feature_code":"PPL",
    "gn:name":"Nayarailagi",
    "gn:population":0,
    "gn:timezone":"Pacific/Fiji",
    "iso:country":"FJ",
    "name:fij_x_preferred":[
        "Nayarailagi"
    ],
    "name:fij_x_variant":[
        "Nayarailangi"
    ],
    "wof:name":"Nayarailagi",
    "wof:placetype":"locality"
},
  "geometry": {"coordinates":[179.06209999999999,-16.6203],"type":"Point"}
}