{
  "type": "Feature",
  "properties": {
    "gn:admin1_code":"02",
    "gn:admin2_code":"4036132",
    "gn:asciiname":"Tokalau",
    "gn:country_code":"FJ",
    "gn:dem":6,
    "gn:feature_class":"P",
    "gn:feature_code":"PPL",
    "gn:name":"Tokalau",
    "gn:population":0,
    "gn:timezone":"Pacific/Fiji",
    "iso:country":"FJ",
    "name:fij_x_preferred":[
        "Tokalau"
    ],
    "wof:name":"Tokalau",
    "wof:placetype":"locality"
},
  "geometry": {"coordinates":[-178.97243,-18.9304],"type":"Point"}
}