{
  "type": "Feature",
  "properties": {
    "gn:admin1_code":"03",
    "gn:admin2_code":"2197820",
    "gn:asciiname":"Nabalebale",
    "gn:country_code":"FJ",
    "gn:dem":33,
    "gn:feature_class":"P",
    "gn:feature_code":"PPL",
    "gn:name":"Nabalebale",
    "gn:population":0,
    "gn:timezone":"Pacific/Fiji",
    "iso:country":"FJ",
    "name:fij_x_preferred":[
        "Nabalebale"
    ],
    "name:fij_x_variant":[
        "Naimbalembale"
    ],
    "wof:name":"Nabalebale",
    "wof:placetype":"locality"
},
  "geometry": {"coordinates":[179.55101999999999,-16.77509],"type":"Point"}
}