{
  "type": "Feature",
  "properties": {
    "gn:admin1_code":"05",
    "gn:admin2_code":"2203798",
    "gn:asciiname":"Vadraulailai Settlement",
    "gn:country_code":"FJ",
    "gn:dem":13,
    "gn:feature_class":"P",
    "gn:feature_code":"PPL",
    "gn:name":"Vadraulailai Settlement",
    "gn:population":0,
    "gn:timezone":"Pacific/Fiji",
    "iso:country":"FJ",
    "name:fij_x_preferred":[
        "Vadraulailai Settlement"
    ],
    "wof:name":"Vadraulailai Settlement",
    "wof:placetype":"locality"
},
  "geometry": {"coordinates":[177.66806,-17.53485],"type":"Point"}
}