{
  "type": "Feature",
  "properties": {
    "gn:admin1_code":"01",
    "gn:admin2_code":"2203150",
    "gn:asciiname":"Waila Settlement",
    "gn:country_code":"FJ",
    "gn:dem":8,
    "gn:feature_class":"P",
    "gn:feature_code":"PPL",
    "gn:name":"Waila Settlement",
    "gn:population":0,
    "gn:timezone":"Pacific/Fiji",
    "iso:country":"FJ",
    "name:fij_x_preferred":[
        "Waila Settlement"
    ],
    "wof:name":"Waila Settlement",
    "wof:placetype":"locality"
},
  "geometry": {"coordinates":[178.51915,-18.02802],"type":"Point"}
}