{
  "type": "Feature",
  "properties": {
    "gn:admin1_code":"01",
    "gn:admin2_code":"2198411",
    "gn:asciiname":"Lalati",
    "gn:country_code":"FJ",
    "gn:dem":14,
    "gn:feature_class":"P",
    "gn:feature_code":"PPL",
    "gn:name":"Lalati",
    "gn:population":0,
    "gn:timezone":"Pacific/Fiji",
    "iso:country":"FJ",
    "name:fij_x_preferred":[
        "Lalati"
    ],
    "wof:name":"Lalati",
    "wof:placetype":"locality"
},
  "geometry": {"coordinates":[178.14826000000005,-18.37605],"type":"Point"}
}