{
  "type": "Feature",
  "properties": {
    "gn:admin1_code":"03",
    "gn:admin2_code":"2203651",
    "gn:asciiname":"Nawaca",
    "gn:country_code":"FJ",
    "gn:dem":21,
    "gn:feature_class":"P",
    "gn:feature_code":"PPL",
    "gn:name":"Nawaca",
    "gn:population":0,
    "gn:timezone":"Pacific/Fiji",
    "iso:country":"FJ",
    "name:fij_x_preferred":[
        "Nawaca"
    ],
    "name:fij_x_variant":[
        "Nawatha"
    ],
    "wof:name":"Nawaca",
    "wof:placetype":"locality"
},
  "geometry": {"coordinates":[178.65875,-16.90333],"type":"Point"}
}