{
  "type": "Feature",
  "properties": {
    "gn:admin1_code":"01",
    "gn:admin2_code":"2198131",
    "gn:asciiname":"Nayavu",
    "gn:country_code":"FJ",
    "gn:dem":39,
    "gn:feature_class":"P",
    "gn:feature_code":"PPL",
    "gn:name":"Nayavu",
    "gn:population":0,
    "gn:timezone":"Pacific/Fiji",
    "iso:country":"FJ",
    "name:fij_x_preferred":[
        "Nayavu"
    ],
    "wof:name":"Nayavu",
    "wof:placetype":"locality"
},
  "geometry": {"coordinates":[178.36317,-17.69337999999999],"type":"Point"}
}