{
  "type": "Feature",
  "properties": {
    "gn:admin1_code":"01",
    "gn:admin2_code":"2203150",
    "gn:asciiname":"Naivucini",
    "gn:country_code":"FJ",
    "gn:dem":35,
    "gn:feature_class":"P",
    "gn:feature_code":"PPL",
    "gn:name":"Naivucini",
    "gn:population":0,
    "gn:timezone":"Pacific/Fiji",
    "iso:country":"FJ",
    "name:fij_x_preferred":[
        "Naivucini"
    ],
    "name:fij_x_variant":[
        "Naivuthini"
    ],
    "wof:name":"Naivucini",
    "wof:placetype":"locality"
},
  "geometry": {"coordinates":[178.26486,-17.84062999999999],"type":"Point"}
}