{
  "type": "Feature",
  "properties": {
    "gn:admin1_code":"02",
    "gn:admin2_code":"8617786",
    "gn:asciiname":"Waikucura Settlement",
    "gn:country_code":"FJ",
    "gn:dem":12,
    "gn:feature_class":"P",
    "gn:feature_code":"PPL",
    "gn:name":"Waikucura Settlement",
    "gn:population":0,
    "gn:timezone":"Pacific/Fiji",
    "iso:country":"FJ",
    "name:fij_x_preferred":[
        "Waikucura Settlement"
    ],
    "wof:name":"Waikucura Settlement",
    "wof:placetype":"locality"
},
  "geometry": {"coordinates":[178.46343999999999,-18.96827],"type":"Point"}
}