{
  "type": "Feature",
  "properties": {
    "gn:admin1_code":"3.0",
    "gn:asciiname":"Vunimoli",
    "gn:country_code":"FJ",
    "gn:dem":57,
    "gn:feature_class":"P",
    "gn:feature_code":"PPL",
    "gn:name":"Vunimoli",
    "gn:population":0,
    "gn:timezone":"Pacific/Fiji",
    "iso:country":"FJ",
    "name:fij_x_preferred":[
        "Vunimoli"
    ],
    "wof:name":"Vunimoli",
    "wof:placetype":"locality"
},
  "geometry": {"coordinates":[179.23333,-16.45],"type":"Point"}
}