{
  "type": "Feature",
  "properties": {
    "iso:country":"FJ",
    "name:pol_x_preferred":[
        "Deuba"
    ],
    "qs:gn_pop":0,
    "qs:name":"Deuba",
    "qs:name_adm0":"Fiji",
    "qs:name_adm1":"Central",
    "qs:photos":171,
    "qs:photos_1k":35,
    "qs:photos_9k":1,
    "qs:photos_9r":4,
    "qs:photos_all":171,
    "qs:photos_sr":4,
    "qs:placetype":"Town",
    "qs:pop_sr":"0",
    "qs:woe_adm0":23424813,
    "wof:name":"Deuba",
    "wof:placetype":"locality"
},
  "geometry": {"coordinates":[177.904357,-18.24003],"type":"Point"}
}