{
  "type": "Feature",
  "properties": {
    "gn:admin1_code":"03",
    "gn:admin2_code":"2203651",
    "gn:asciiname":"Banikea",
    "gn:country_code":"FJ",
    "gn:dem":180,
    "gn:feature_class":"P",
    "gn:feature_code":"PPL",
    "gn:name":"Banikea",
    "gn:population":0,
    "gn:timezone":"Pacific/Fiji",
    "iso:country":"FJ",
    "name:fij_x_preferred":[
        "Banikea"
    ],
    "name:und_x_variant":[
        "Mbanikeya",
        "Mbanikea"
    ],
    "wof:name":"Banikea",
    "wof:placetype":"locality"
},
  "geometry": {"coordinates":[178.74188000000001,-16.76032],"type":"Point"}
}