{
  "type": "Feature",
  "properties": {
    "gn:admin1_code":"02",
    "gn:admin2_code":"2204318",
    "gn:asciiname":"Matadodo Settlement",
    "gn:country_code":"FJ",
    "gn:dem":7,
    "gn:feature_class":"P",
    "gn:feature_code":"PPL",
    "gn:name":"Matadodo Settlement",
    "gn:population":0,
    "gn:timezone":"Pacific/Fiji",
    "iso:country":"FJ",
    "name:fij_x_preferred":[
        "Matadodo Settlement"
    ],
    "wof:name":"Matadodo Settlement",
    "wof:placetype":"locality"
},
  "geometry": {"coordinates":[178.74323000000001,-17.77365],"type":"Point"}
}