{
  "type": "Feature",
  "properties": {
    "gn:admin1_code":"05",
    "gn:admin2_code":"2201984",
    "gn:asciiname":"Naduri",
    "gn:country_code":"FJ",
    "gn:dem":12,
    "gn:feature_class":"P",
    "gn:feature_code":"PPL",
    "gn:name":"Naduri",
    "gn:population":0,
    "gn:timezone":"Pacific/Fiji",
    "iso:country":"FJ",
    "name:fij_x_preferred":[
        "Naduri"
    ],
    "name:und_x_variant":[
        "Nanduri"
    ],
    "wof:name":"Naduri",
    "wof:placetype":"locality"
},
  "geometry": {"coordinates":[177.55819,-18.07798],"type":"Point"}
}