{
  "type": "Feature",
  "properties": {
    "gn:admin1_code":"02",
    "gn:admin2_code":"8617786",
    "gn:asciiname":"Manuka",
    "gn:country_code":"FJ",
    "gn:dem":6,
    "gn:feature_class":"P",
    "gn:feature_code":"PPL",
    "gn:name":"Manuka",
    "gn:population":0,
    "gn:timezone":"Pacific/Fiji",
    "iso:country":"FJ",
    "name:ceb_x_preferred":[
        "Manuka"
    ],
    "name:fij_x_preferred":[
        "Manuka"
    ],
    "name:swe_x_preferred":[
        "Manuka"
    ],
    "name:ton_x_preferred":[
        "Manuka"
    ],
    "name:und_x_variant":[
        "Nambouwalu",
        "Mbualu",
        "Manuku"
    ],
    "wof:name":"Manuka",
    "wof:placetype":"locality"
},
  "geometry": {"coordinates":[178.47012000000001,-18.88945],"type":"Point"}
}