{
  "type": "Feature",
  "properties": {
    "gn:admin1_code":"03",
    "gn:admin2_code":"2197820",
    "gn:asciiname":"Nacula",
    "gn:country_code":"FJ",
    "gn:dem":57,
    "gn:feature_class":"P",
    "gn:feature_code":"PPL",
    "gn:name":"Nacula",
    "gn:population":0,
    "gn:timezone":"Pacific/Fiji",
    "iso:country":"FJ",
    "name:ceb_x_preferred":[
        "Nathula Island"
    ],
    "name:fij_x_preferred":[
        "Nacula"
    ],
    "name:fij_x_variant":[
        "Nathula"
    ],
    "name:fra_x_preferred":[
        "Nacula"
    ],
    "name:hif_x_preferred":[
        "Nacula"
    ],
    "name:ita_x_preferred":[
        "Nacula"
    ],
    "name:nld_x_preferred":[
        "Nacula"
    ],
    "name:por_x_preferred":[
        "Nacula"
    ],
    "name:rus_x_preferred":[
        "\u041d\u0430\u0442\u0443\u043b\u0430"
    ],
    "wof:name":"Nacula",
    "wof:placetype":"locality"
},
  "geometry": {"coordinates":[179.67993999999999,-16.41021],"type":"Point"}
}