{
  "type": "Feature",
  "properties": {
    "gn:admin1_code":"05",
    "gn:admin2_code":"2201984",
    "gn:asciiname":"Naevuevu",
    "gn:country_code":"FJ",
    "gn:dem":4,
    "gn:feature_class":"P",
    "gn:feature_code":"PPL",
    "gn:name":"Naevuevu",
    "gn:population":0,
    "gn:timezone":"Pacific/Fiji",
    "iso:country":"FJ",
    "name:und_x_variant":[
        "Navuevu",
        "Nasalau",
        "Naevuevu"
    ],
    "wof:name":"Naevuevu",
    "wof:placetype":"locality"
},
  "geometry": {"coordinates":[177.44218000000001,-18.152],"type":"Point"}
}