{
  "type": "Feature",
  "properties": {
    "gn:admin1_code":"05",
    "gn:admin2_code":"2198946",
    "gn:asciiname":"Nadavacia Settlement",
    "gn:country_code":"FJ",
    "gn:dem":124,
    "gn:feature_class":"P",
    "gn:feature_code":"PPL",
    "gn:name":"Nadavacia Settlement",
    "gn:population":0,
    "gn:timezone":"Pacific/Fiji",
    "iso:country":"FJ",
    "name:fij_x_preferred":[
        "Nadavacia Settlement"
    ],
    "wof:name":"Nadavacia Settlement",
    "wof:placetype":"locality"
},
  "geometry": {"coordinates":[178.36046999999999,-17.5403],"type":"Point"}
}