{
  "type": "Feature",
  "properties": {
    "gn:admin1_code":"03",
    "gn:asciiname":"Koronatonga",
    "gn:country_code":"FJ",
    "gn:dem":21,
    "gn:feature_class":"P",
    "gn:feature_code":"PPL",
    "gn:name":"Koronatonga",
    "gn:population":0,
    "gn:timezone":"Pacific/Fiji",
    "iso:country":"FJ",
    "wof:name":"Koronatonga",
    "wof:placetype":"locality"
},
  "geometry": {"coordinates":[179.53333000000001,-16.63332999999999],"type":"Point"}
}