{
  "type": "Feature",
  "properties": {
    "gn:admin1_code":"03",
    "gn:admin2_code":"2203875",
    "gn:asciiname":"Mataniwai",
    "gn:country_code":"FJ",
    "gn:dem":1,
    "gn:feature_class":"P",
    "gn:feature_code":"PPL",
    "gn:name":"Mataniwai",
    "gn:population":0,
    "gn:timezone":"Pacific/Fiji",
    "iso:country":"FJ",
    "name:fij_x_preferred":[
        "Mataniwai"
    ],
    "wof:name":"Mataniwai",
    "wof:placetype":"locality"
},
  "geometry": {"coordinates":[179.42241000000001,-16.33965],"type":"Point"}
}