{
  "type": "Feature",
  "properties": {
    "gn:admin1_code":"05",
    "gn:admin2_code":"2198946",
    "gn:asciiname":"Sarava Settlement",
    "gn:country_code":"FJ",
    "gn:dem":42,
    "gn:feature_class":"P",
    "gn:feature_code":"PPL",
    "gn:name":"Sarava Settlement",
    "gn:population":0,
    "gn:timezone":"Pacific/Fiji",
    "iso:country":"FJ",
    "name:fij_x_preferred":[
        "Sarava Settlement"
    ],
    "wof:name":"Sarava Settlement",
    "wof:placetype":"locality"
},
  "geometry": {"coordinates":[178.30032,-17.52296],"type":"Point"}
}