{
  "type": "Feature",
  "properties": {
    "gn:admin1_code":"00",
    "gn:asciiname":"Kana",
    "gn:country_code":"FJ",
    "gn:dem":-9999,
    "gn:feature_class":"P",
    "gn:feature_code":"PPL",
    "gn:name":"Kana",
    "gn:population":0,
    "gn:timezone":"Pacific/Fiji",
    "iso:country":"FJ",
    "name:afr_x_preferred":[
        "Kana"
    ],
    "name:ara_x_preferred":[
        "\u0643\u0627\u0646\u0627"
    ],
    "name:bcl_x_preferred":[
        "Kana"
    ],
    "name:bel_x_preferred":[
        "\u041a\u0430\u043d\u0430"
    ],
    "name:ben_x_preferred":[
        "\u0995\u09be\u09a8\u09be"
    ],
    "name:bos_x_preferred":[
        "Kana"
    ],
    "name:cat_x_preferred":[
        "Kana"
    ],
    "name:cdo_x_preferred":[
        "Kana"
    ],
    "name:ces_x_preferred":[
        "Kana"
    ],
    "name:ckb_x_preferred":[
        "\u06a9\u0627\u0646\u0627"
    ],
    "name:dan_x_preferred":[
        "Kana"
    ],
    "name:deu_x_preferred":[
        "Japanische Schrift#Kana"
    ],
    "name:est_x_preferred":[
        "Kana"
    ],
    "name:eus_x_preferred":[
        "Kana"
    ],
    "name:fao_x_preferred":[
        "Kana"
    ],
    "name:fas_x_preferred":[
        "\u06a9\u0627\u0646\u0627"
    ],
    "name:fij_x_preferred":[
        "Kana"
    ],
    "name:fin_x_preferred":[
        "Kana"
    ],
    "name:fra_x_preferred":[
        "Kana"
    ],
    "name:glg_x_preferred":[
        "Kana"
    ],
    "name:hak_x_preferred":[
        "Kana"
    ],
    "name:hin_x_preferred":[
        "\u0915\u093e\u0928\u093e"
    ],
    "name:hrv_x_preferred":[
        "Kana"
    ],
    "name:hun_x_preferred":[
        "Kana"
    ],
    "name:ind_x_preferred":[
        "Aksara kana"
    ],
    "name:ita_x_preferred":[
        "Kana"
    ],
    "name:jav_x_preferred":[
        "Kana"
    ],
    "name:jbo_x_preferred":[
        "ponslakyle'u"
    ],
    "name:jpn_x_preferred":[
        "\u4eee\u540d"
    ],
    "name:kor_x_preferred":[
        "\uac00\ub098"
    ],
    "name:lat_x_preferred":[
        "Kana"
    ],
    "name:mlg_x_preferred":[
        "Kana"
    ],
    "name:msa_x_preferred":[
        "Tulisan Kana"
    ],
    "name:nld_x_preferred":[
        "Kana"
    ],
    "name:nno_x_preferred":[
        "Kana"
    ],
    "name:nor_x_preferred":[
        "Kana"
    ],
    "name:pol_x_preferred":[
        "Kana"
    ],
    "name:por_x_preferred":[
        "Kana"
    ],
    "name:ron_x_preferred":[
        "Kana"
    ],
    "name:rus_x_preferred":[
        "\u041a\u0430\u043d\u0430"
    ],
    "name:sco_x_preferred":[
        "Kana"
    ],
    "name:slk_x_preferred":[
        "Kana"
    ],
    "name:spa_x_preferred":[
        "Kana"
    ],
    "name:srp_x_preferred":[
        "Kana"
    ],
    "name:sun_x_preferred":[
        "Kana"
    ],
    "name:swe_x_preferred":[
        "Kana"
    ],
    "name:szl_x_preferred":[
        "Kana"
    ],
    "name:tgk_x_preferred":[
        "\u041a\u0430\u043d\u0430"
    ],
    "name:tgl_x_preferred":[
        "Kana"
    ],
    "name:tha_x_preferred":[
        "\u0e04\u0e32\u0e19\u0e30"
    ],
    "name:tur_x_preferred":[
        "Kana"
    ],
    "name:ukr_x_preferred":[
        "\u041a\u0430\u043d\u0430"
    ],
    "name:vie_x_preferred":[
        "Kana"
    ],
    "name:wuu_x_preferred":[
        "\u5047\u540d"
    ],
    "name:zho_x_preferred":[
        "\u65e5\u8a9e\u5047\u540d"
    ],
    "wof:name":"Kana",
    "wof:placetype":"locality"
},
  "geometry": {"coordinates":[179.43333000000001,-17.78333],"type":"Point"}
}