{
  "type": "Feature",
  "properties": {
    "gn:admin1_code":"05",
    "gn:admin2_code":"2203798",
    "gn:asciiname":"Toreituni Settlement",
    "gn:country_code":"FJ",
    "gn:dem":148,
    "gn:feature_class":"P",
    "gn:feature_code":"PPL",
    "gn:name":"Toreituni Settlement",
    "gn:population":0,
    "gn:timezone":"Pacific/Fiji",
    "iso:country":"FJ",
    "name:fij_x_preferred":[
        "Toreituni Settlement"
    ],
    "wof:name":"Toreituni Settlement",
    "wof:placetype":"locality"
},
  "geometry": {"coordinates":[177.76236,-17.68393],"type":"Point"}
}