{
  "type": "Feature",
  "properties": {
    "gn:admin1_code":"01",
    "gn:admin2_code":"2198131",
    "gn:asciiname":"Nabouwalu",
    "gn:country_code":"FJ",
    "gn:dem":16,
    "gn:feature_class":"P",
    "gn:feature_code":"PPL",
    "gn:name":"Nabouwalu",
    "gn:population":0,
    "gn:timezone":"Pacific/Fiji",
    "iso:country":"FJ",
    "name:fij_x_preferred":[
        "Nabouwalu"
    ],
    "name:und_x_variant":[
        "Kamba",
        "Nambouwalu"
    ],
    "wof:name":"Nabouwalu",
    "wof:placetype":"locality"
},
  "geometry": {"coordinates":[178.68566999999999,-18.00457],"type":"Point"}
}