{
  "type": "Feature",
  "properties": {
    "gn:admin1_code":"05",
    "gn:admin2_code":"2201984",
    "gn:asciiname":"Nakoro",
    "gn:country_code":"FJ",
    "gn:dem":218,
    "gn:feature_class":"P",
    "gn:feature_code":"PPL",
    "gn:name":"Nakoro",
    "gn:population":0,
    "gn:timezone":"Pacific/Fiji",
    "iso:country":"FJ",
    "name:und_x_variant":[
        "Drio drio",
        "Nakoro"
    ],
    "wof:name":"Nakoro",
    "wof:placetype":"locality"
},
  "geometry": {"coordinates":[177.90181000000001,-17.95006],"type":"Point"}
}