{
  "type": "Feature",
  "properties": {
    "gn:admin1_code":"04",
    "gn:asciiname":"Maftoa",
    "gn:country_code":"FJ",
    "gn:dem":1,
    "gn:feature_class":"P",
    "gn:feature_code":"PPL",
    "gn:name":"Maftoa",
    "gn:population":0,
    "gn:timezone":"Pacific/Fiji",
    "iso:country":"FJ",
    "name:fij_x_preferred":[
        "Maftoa"
    ],
    "wof:name":"Maftoa",
    "wof:placetype":"locality"
},
  "geometry": {"coordinates":[177.0309,-12.49809],"type":"Point"}
}