{
  "type": "Feature",
  "properties": {
    "gn:admin1_code":"01",
    "gn:admin2_code":"2198131",
    "gn:asciiname":"Matai Settlement",
    "gn:country_code":"FJ",
    "gn:dem":26,
    "gn:feature_class":"P",
    "gn:feature_code":"PPL",
    "gn:name":"Matai Settlement",
    "gn:population":0,
    "gn:timezone":"Pacific/Fiji",
    "iso:country":"FJ",
    "name:fij_x_preferred":[
        "Matai Settlement"
    ],
    "wof:name":"Matai Settlement",
    "wof:placetype":"locality"
},
  "geometry": {"coordinates":[178.53646000000001,-17.62363999999999],"type":"Point"}
}