{
  "type": "Feature",
  "properties": {
    "gn:admin1_code":"05",
    "gn:admin2_code":"2198946",
    "gn:asciiname":"Lomalake Settlement",
    "gn:country_code":"FJ",
    "gn:dem":9,
    "gn:feature_class":"P",
    "gn:feature_code":"PPL",
    "gn:name":"Lomalake Settlement",
    "gn:population":0,
    "gn:timezone":"Pacific/Fiji",
    "iso:country":"FJ",
    "name:fij_x_preferred":[
        "Lomalake Settlement"
    ],
    "wof:name":"Lomalake Settlement",
    "wof:placetype":"locality"
},
  "geometry": {"coordinates":[178.14150000000001,-17.31737],"type":"Point"}
}