{
  "type": "Feature",
  "properties": {
    "gn:admin1_code":"03",
    "gn:admin2_code":"2197820",
    "gn:asciiname":"Natuvu",
    "gn:country_code":"FJ",
    "gn:dem":4,
    "gn:feature_class":"P",
    "gn:feature_code":"PPL",
    "gn:name":"Natuvu",
    "gn:population":0,
    "gn:timezone":"Pacific/Fiji",
    "iso:country":"FJ",
    "name:und_x_variant":[
        "Na Tuva",
        "Naturu",
        "Natuvu"
    ],
    "wof:name":"Natuvu",
    "wof:placetype":"locality"
},
  "geometry": {"coordinates":[179.15334999999999,-16.74444],"type":"Point"}
}