{
  "type": "Feature",
  "properties": {
    "gn:admin1_code":"01",
    "gn:admin2_code":"2198411",
    "gn:asciiname":"Wainiveidio Settlement",
    "gn:country_code":"FJ",
    "gn:dem":6,
    "gn:feature_class":"P",
    "gn:feature_code":"PPL",
    "gn:name":"Wainiveidio Settlement",
    "gn:population":0,
    "gn:timezone":"Pacific/Fiji",
    "iso:country":"FJ",
    "name:fij_x_preferred":[
        "Wainiveidio Settlement"
    ],
    "wof:name":"Wainiveidio Settlement",
    "wof:placetype":"locality"
},
  "geometry": {"coordinates":[178.17256,-18.23324],"type":"Point"}
}