{
  "type": "Feature",
  "properties": {
    "gn:admin1_code":"01",
    "gn:admin2_code":"2198411",
    "gn:asciiname":"Taqove Settlement",
    "gn:country_code":"FJ",
    "gn:dem":16,
    "gn:feature_class":"P",
    "gn:feature_code":"PPL",
    "gn:name":"Taqove Settlement",
    "gn:population":0,
    "gn:timezone":"Pacific/Fiji",
    "iso:country":"FJ",
    "name:fij_x_preferred":[
        "Taqove Settlement"
    ],
    "wof:name":"Taqove Settlement",
    "wof:placetype":"locality"
},
  "geometry": {"coordinates":[177.97799999999995,-18.25657],"type":"Point"}
}