{
  "type": "Feature",
  "properties": {
    "gn:admin1_code":"05",
    "gn:admin2_code":"2201984",
    "gn:asciiname":"Nausori",
    "gn:country_code":"FJ",
    "gn:dem":524,
    "gn:feature_class":"P",
    "gn:feature_code":"PPL",
    "gn:name":"Nausori",
    "gn:population":0,
    "gn:timezone":"Pacific/Fiji",
    "iso:country":"FJ",
    "name:ceb_x_preferred":[
        "Nausori"
    ],
    "name:ces_x_preferred":[
        "Nausori"
    ],
    "name:deu_x_preferred":[
        "Nausori"
    ],
    "name:fij_x_preferred":[
        "Nausori"
    ],
    "name:fin_x_preferred":[
        "Nausori"
    ],
    "name:fra_x_preferred":[
        "Nausori"
    ],
    "name:hif_x_preferred":[
        "Nausori"
    ],
    "name:hin_x_preferred":[
        "\u0928\u0909\u0938\u094b\u0930\u0940"
    ],
    "name:jpn_x_preferred":[
        "\u30ca\u30a6\u30bd\u30ea"
    ],
    "name:kor_x_preferred":[
        "\ub098\uc6b0\uc18c\ub9ac"
    ],
    "name:lit_x_preferred":[
        "Nausoris"
    ],
    "name:nld_x_preferred":[
        "Nausori"
    ],
    "name:pol_x_preferred":[
        "Nausori"
    ],
    "name:ron_x_preferred":[
        "Nausori"
    ],
    "name:rus_x_preferred":[
        "\u041d\u0430\u0443\u0441\u043e\u0440\u0438"
    ],
    "name:spa_x_preferred":[
        "Nausori"
    ],
    "name:swe_x_preferred":[
        "Nausori"
    ],
    "name:tam_x_preferred":[
        "\u0ba8\u0bb5\u0bc1\u0b9a\u0bcb\u0bb0\u0bbf"
    ],
    "name:vep_x_preferred":[
        "Nausori"
    ],
    "name:zho_x_preferred":[
        "\u7459\u7d22\u91cc"
    ],
    "wof:name":"Nausori",
    "wof:placetype":"locality"
},
  "geometry": {"coordinates":[177.61099999999999,-17.81768],"type":"Point"}
}