{
  "type": "Feature",
  "properties": {
    "gn:admin1_code":"05",
    "gn:admin2_code":"2201984",
    "gn:asciiname":"Nausori",
    "gn:country_code":"FJ",
    "gn:dem":524,
    "gn:feature_class":"P",
    "gn:feature_code":"PPL",
    "gn:name":"Nausori",
    "gn:population":0,
    "gn:timezone":"Pacific/Fiji",
    "iso:country":"FJ",
    "name:fij_x_preferred":[
        "Nausori"
    ],
    "wof:name":"Nausori",
    "wof:placetype":"locality"
},
  "geometry": {"coordinates":[177.61099999999999,-17.81768],"type":"Point"}
}