{
  "type": "Feature",
  "properties": {
    "gn:admin1_code":"01",
    "gn:admin2_code":"2198411",
    "gn:asciiname":"Navutulevu",
    "gn:country_code":"FJ",
    "gn:dem":7,
    "gn:feature_class":"P",
    "gn:feature_code":"PPL",
    "gn:name":"Navutulevu",
    "gn:population":0,
    "gn:timezone":"Pacific/Fiji",
    "iso:country":"FJ",
    "name:und_x_variant":[
        "Vutu Levu",
        "Navutulevu"
    ],
    "wof:name":"Navutulevu",
    "wof:placetype":"locality"
},
  "geometry": {"coordinates":[177.80608000000001,-18.23712],"type":"Point"}
}