{
  "type": "Feature",
  "properties": {
    "gn:admin1_code":"03",
    "gn:admin2_code":"2203651",
    "gn:asciiname":"Nadua Settlement",
    "gn:country_code":"FJ",
    "gn:dem":55,
    "gn:feature_class":"P",
    "gn:feature_code":"PPL",
    "gn:name":"Nadua Settlement",
    "gn:population":0,
    "gn:timezone":"Pacific/Fiji",
    "iso:country":"FJ",
    "name:fij_x_preferred":[
        "Nadua Settlement"
    ],
    "wof:name":"Nadua Settlement",
    "wof:placetype":"locality"
},
  "geometry": {"coordinates":[178.75766999999999,-16.93452000000001],"type":"Point"}
}