{
  "type": "Feature",
  "properties": {
    "gn:admin1_code":"05",
    "gn:admin2_code":"2203798",
    "gn:asciiname":"Naviago",
    "gn:country_code":"FJ",
    "gn:dem":5,
    "gn:feature_class":"P",
    "gn:feature_code":"PPL",
    "gn:name":"Naviago",
    "gn:population":0,
    "gn:timezone":"Pacific/Fiji",
    "iso:country":"FJ",
    "name:fij_x_preferred":[
        "Naviago"
    ],
    "name:und_x_variant":[
        "Navivanga",
        "Naviyango"
    ],
    "wof:name":"Naviago",
    "wof:placetype":"locality"
},
  "geometry": {"coordinates":[177.4973,-17.5892],"type":"Point"}
}