{
  "type": "Feature",
  "properties": {
    "gn:admin1_code":"03",
    "gn:admin2_code":"2197820",
    "gn:asciiname":"Matanitana Settlement",
    "gn:country_code":"FJ",
    "gn:dem":26,
    "gn:feature_class":"P",
    "gn:feature_code":"PPL",
    "gn:name":"Matanitana Settlement",
    "gn:population":0,
    "gn:timezone":"Pacific/Fiji",
    "iso:country":"FJ",
    "name:fij_x_preferred":[
        "Matanitana Settlement"
    ],
    "wof:name":"Matanitana Settlement",
    "wof:placetype":"locality"
},
  "geometry": {"coordinates":[179.012,-16.79379],"type":"Point"}
}