{
  "type": "Feature",
  "properties": {
    "gn:admin1_code":"03",
    "gn:admin2_code":"2203875",
    "gn:asciiname":"Namatadogo Settlement",
    "gn:country_code":"FJ",
    "gn:dem":25,
    "gn:feature_class":"P",
    "gn:feature_code":"PPL",
    "gn:name":"Namatadogo Settlement",
    "gn:population":0,
    "gn:timezone":"Pacific/Fiji",
    "iso:country":"FJ",
    "name:fij_x_preferred":[
        "Namatadogo Settlement"
    ],
    "wof:name":"Namatadogo Settlement",
    "wof:placetype":"locality"
},
  "geometry": {"coordinates":[178.98328000000001,-16.62462],"type":"Point"}
}