{
  "type": "Feature",
  "properties": {
    "gn:admin1_code":"1.0",
    "gn:admin2_code":"2198131.0",
    "gn:asciiname":"Vuci",
    "gn:country_code":"FJ",
    "gn:dem":4,
    "gn:feature_class":"P",
    "gn:feature_code":"PPL",
    "gn:name":"Vuci",
    "gn:population":0,
    "gn:timezone":"Pacific/Fiji",
    "iso:country":"FJ",
    "name:fij_x_preferred":[
        "Vuci"
    ],
    "name:fij_x_variant":[
        "Vuthi"
    ],
    "wof:name":"Vuci",
    "wof:placetype":"locality"
},
  "geometry": {"coordinates":[178.59128000000001,-18.08526],"type":"Point"}
}