{
  "type": "Feature",
  "properties": {
    "gn:admin1_code":"01",
    "gn:admin2_code":"2198131",
    "gn:asciiname":"Waidawara Settlement",
    "gn:country_code":"FJ",
    "gn:dem":22,
    "gn:feature_class":"P",
    "gn:feature_code":"PPL",
    "gn:name":"Waidawara Settlement",
    "gn:population":0,
    "gn:timezone":"Pacific/Fiji",
    "iso:country":"FJ",
    "name:fij_x_preferred":[
        "Waidawara Settlement"
    ],
    "wof:name":"Waidawara Settlement",
    "wof:placetype":"locality"
},
  "geometry": {"coordinates":[178.34788,-17.81853],"type":"Point"}
}