{
  "type": "Feature",
  "properties": {
    "gn:admin1_code":"02",
    "gn:admin2_code":"8617786",
    "gn:asciiname":"Nakoro Settlement",
    "gn:country_code":"FJ",
    "gn:dem":11,
    "gn:feature_class":"P",
    "gn:feature_code":"PPL",
    "gn:name":"Nakoro Settlement",
    "gn:population":0,
    "gn:timezone":"Pacific/Fiji",
    "iso:country":"FJ",
    "name:fij_x_preferred":[
        "Nakoro Settlement"
    ],
    "wof:name":"Nakoro Settlement",
    "wof:placetype":"locality"
},
  "geometry": {"coordinates":[178.47583999999995,-18.98527],"type":"Point"}
}