{
  "type": "Feature",
  "properties": {
    "gn:admin1_code":"01",
    "gn:admin2_code":"2198131",
    "gn:asciiname":"Navuca Settlement",
    "gn:country_code":"FJ",
    "gn:dem":42,
    "gn:feature_class":"P",
    "gn:feature_code":"PPL",
    "gn:name":"Navuca Settlement",
    "gn:population":0,
    "gn:timezone":"Pacific/Fiji",
    "iso:country":"FJ",
    "name:fij_x_preferred":[
        "Navuca Settlement"
    ],
    "wof:name":"Navuca Settlement",
    "wof:placetype":"locality"
},
  "geometry": {"coordinates":[178.51752999999999,-17.75611],"type":"Point"}
}