{
  "type": "Feature",
  "properties": {
    "gn:admin1_code":"01",
    "gn:admin2_code":"2203150",
    "gn:asciiname":"Waisa Settlement",
    "gn:country_code":"FJ",
    "gn:dem":32,
    "gn:feature_class":"P",
    "gn:feature_code":"PPL",
    "gn:name":"Waisa Settlement",
    "gn:population":0,
    "gn:timezone":"Pacific/Fiji",
    "iso:country":"FJ",
    "name:fij_x_preferred":[
        "Waisa Settlement"
    ],
    "wof:name":"Waisa Settlement",
    "wof:placetype":"locality"
},
  "geometry": {"coordinates":[178.33153999999999,-17.89886],"type":"Point"}
}