{
  "type": "Feature",
  "properties": {
    "gn:admin1_code":"00",
    "gn:asciiname":"Namacu",
    "gn:country_code":"FJ",
    "gn:dem":3,
    "gn:feature_class":"P",
    "gn:feature_code":"PPL",
    "gn:name":"Namacu",
    "gn:population":0,
    "gn:timezone":"Pacific/Fiji",
    "iso:country":"FJ",
    "name:eng_x_preferred":[
        "Namacu"
    ],
    "wof:name":"Namacu",
    "wof:placetype":"locality"
},
  "geometry": {"coordinates":[179.43308999999999,-17.33462],"type":"Point"}
}