{
  "type": "Feature",
  "properties": {
    "gn:admin1_code":"04",
    "gn:asciiname":"Lau",
    "gn:country_code":"FJ",
    "gn:dem":7,
    "gn:feature_class":"P",
    "gn:feature_code":"PPL",
    "gn:name":"Lau",
    "gn:population":0,
    "gn:timezone":"Pacific/Fiji",
    "iso:country":"FJ",
    "name:ceb_x_preferred":[
        "Lau"
    ],
    "name:ces_x_preferred":[
        "Lau"
    ],
    "name:deu_x_preferred":[
        "Lau"
    ],
    "name:fra_x_preferred":[
        "Lau"
    ],
    "name:heb_x_preferred":[
        "\u05dc\u05d0\u05d5"
    ],
    "name:nld_x_preferred":[
        "Lau"
    ],
    "name:swe_x_preferred":[
        "Lau"
    ],
    "name:ukr_x_preferred":[
        "LAU"
    ],
    "wof:name":"Lau",
    "wof:placetype":"locality"
},
  "geometry": {"coordinates":[177.04823000000005,-12.50896],"type":"Point"}
}