{
  "type": "Feature",
  "properties": {
    "gn:admin1_code":"03",
    "gn:admin2_code":"2203651",
    "gn:asciiname":"Nakorovou",
    "gn:country_code":"FJ",
    "gn:dem":15,
    "gn:feature_class":"P",
    "gn:feature_code":"PPL",
    "gn:name":"Nakorovou",
    "gn:population":0,
    "gn:timezone":"Pacific/Fiji",
    "iso:country":"FJ",
    "name:fij_x_preferred":[
        "Nakorovou"
    ],
    "name:fij_x_variant":[
        "Korovou"
    ],
    "wof:name":"Nakorovou",
    "wof:placetype":"locality"
},
  "geometry": {"coordinates":[179.0256,-16.82783],"type":"Point"}
}