{
  "type": "Feature",
  "properties": {
    "gn:admin1_code":"05",
    "gn:admin2_code":"2201984",
    "gn:asciiname":"Nabobobo Settlement",
    "gn:country_code":"FJ",
    "gn:dem":56,
    "gn:feature_class":"P",
    "gn:feature_code":"PPL",
    "gn:name":"Nabobobo Settlement",
    "gn:population":0,
    "gn:timezone":"Pacific/Fiji",
    "iso:country":"FJ",
    "name:fij_x_preferred":[
        "Nabobobo Settlement"
    ],
    "wof:name":"Nabobobo Settlement",
    "wof:placetype":"locality"
},
  "geometry": {"coordinates":[177.78502,-17.91079],"type":"Point"}
}