{
  "type": "Feature",
  "properties": {
    "gn:admin1_code":"01",
    "gn:admin2_code":"2198411",
    "gn:asciiname":"Nacegacega Settlement",
    "gn:country_code":"FJ",
    "gn:dem":188,
    "gn:feature_class":"P",
    "gn:feature_code":"PPL",
    "gn:name":"Nacegacega Settlement",
    "gn:population":0,
    "gn:timezone":"Pacific/Fiji",
    "iso:country":"FJ",
    "name:fij_x_preferred":[
        "Nacegacega Settlement"
    ],
    "wof:name":"Nacegacega Settlement",
    "wof:placetype":"locality"
},
  "geometry": {"coordinates":[177.85478999999995,-18.15754],"type":"Point"}
}