{
  "type": "Feature",
  "properties": {
    "gn:admin1_code":"05",
    "gn:admin2_code":"2203798",
    "gn:asciiname":"Nawaqadamu",
    "gn:country_code":"FJ",
    "gn:dem":225,
    "gn:feature_class":"P",
    "gn:feature_code":"PPL",
    "gn:name":"Nawaqadamu",
    "gn:population":0,
    "gn:timezone":"Pacific/Fiji",
    "iso:country":"FJ",
    "name:fij_x_preferred":[
        "Nawaqadamu"
    ],
    "name:und_x_variant":[
        "Nawanggandamu"
    ],
    "wof:name":"Nawaqadamu",
    "wof:placetype":"locality"
},
  "geometry": {"coordinates":[177.43648000000005,-17.92898],"type":"Point"}
}