{
  "type": "Feature",
  "properties": {
    "gn:admin1_code":"03",
    "gn:admin2_code":"2197820",
    "gn:asciiname":"Delaikatoba Settlement",
    "gn:country_code":"FJ",
    "gn:dem":61,
    "gn:feature_class":"P",
    "gn:feature_code":"PPL",
    "gn:name":"Delaikatoba Settlement",
    "gn:population":0,
    "gn:timezone":"Pacific/Fiji",
    "iso:country":"FJ",
    "name:fij_x_preferred":[
        "Delaikatoba Settlement"
    ],
    "wof:name":"Delaikatoba Settlement",
    "wof:placetype":"locality"
},
  "geometry": {"coordinates":[179.92307,-17.00396],"type":"Point"}
}