{
  "type": "Feature",
  "properties": {
    "gn:admin1_code":"02",
    "gn:admin2_code":"2204318",
    "gn:asciiname":"Dalice Settlement",
    "gn:country_code":"FJ",
    "gn:dem":27,
    "gn:feature_class":"P",
    "gn:feature_code":"PPL",
    "gn:name":"Dalice Settlement",
    "gn:population":0,
    "gn:timezone":"Pacific/Fiji",
    "iso:country":"FJ",
    "name:fij_x_preferred":[
        "Dalice Settlement"
    ],
    "name:und_x_variant":[
        "Dalice",
        "Ndalithi",
        "Ndalithe"
    ],
    "wof:name":"Dalice Settlement",
    "wof:placetype":"locality"
},
  "geometry": {"coordinates":[179.39937,-17.79981],"type":"Point"}
}