{
  "type": "Feature",
  "properties": {
    "gn:admin1_code":"03",
    "gn:admin2_code":"2197820",
    "gn:asciiname":"Bagasau",
    "gn:country_code":"FJ",
    "gn:dem":8,
    "gn:feature_class":"P",
    "gn:feature_code":"PPL",
    "gn:name":"Bagasau",
    "gn:population":0,
    "gn:timezone":"Pacific/Fiji",
    "iso:country":"FJ",
    "name:fij_x_preferred":[
        "Bagasau"
    ],
    "name:fij_x_variant":[
        "Mbangasau"
    ],
    "wof:name":"Bagasau",
    "wof:placetype":"locality"
},
  "geometry": {"coordinates":[179.72613999999999,-16.71666],"type":"Point"}
}