{
  "type": "Feature",
  "properties": {
    "gn:admin1_code":"01",
    "gn:admin2_code":"2198131",
    "gn:asciiname":"Mokani",
    "gn:country_code":"FJ",
    "gn:dem":5,
    "gn:feature_class":"P",
    "gn:feature_code":"PPL",
    "gn:name":"Mokani",
    "gn:population":0,
    "gn:timezone":"Pacific/Fiji",
    "iso:country":"FJ",
    "name:fij_x_preferred":[
        "Mokani"
    ],
    "wof:name":"Mokani",
    "wof:placetype":"locality"
},
  "geometry": {"coordinates":[178.60481999999999,-18.00919],"type":"Point"}
}