{
  "type": "Feature",
  "properties": {
    "gn:admin1_code":"01",
    "gn:admin2_code":"2198131",
    "gn:asciiname":"Bougainville Settlement",
    "gn:country_code":"FJ",
    "gn:dem":205,
    "gn:feature_class":"P",
    "gn:feature_code":"PPL",
    "gn:name":"Bougainville Settlement",
    "gn:population":0,
    "gn:timezone":"Pacific/Fiji",
    "iso:country":"FJ",
    "name:eng_x_preferred":[
        "Bougainville Settlement"
    ],
    "wof:name":"Bougainville Settlement",
    "wof:placetype":"locality"
},
  "geometry": {"coordinates":[178.42021,-17.76776],"type":"Point"}
}