{
  "type": "Feature",
  "properties": {
    "gn:admin1_code":"03",
    "gn:admin2_code":"2197820",
    "gn:asciiname":"Navolivoli Settlement",
    "gn:country_code":"FJ",
    "gn:dem":56,
    "gn:feature_class":"P",
    "gn:feature_code":"PPL",
    "gn:name":"Navolivoli Settlement",
    "gn:population":0,
    "gn:timezone":"Pacific/Fiji",
    "iso:country":"FJ",
    "name:fij_x_preferred":[
        "Navolivoli Settlement"
    ],
    "wof:name":"Navolivoli Settlement",
    "wof:placetype":"locality"
},
  "geometry": {"coordinates":[179.91583,-17.0048],"type":"Point"}
}