{
  "type": "Feature",
  "properties": {
    "gn:admin1_code":"02",
    "gn:admin2_code":"2204318",
    "gn:asciiname":"Urata Settlement",
    "gn:country_code":"FJ",
    "gn:dem":27,
    "gn:feature_class":"P",
    "gn:feature_code":"PPL",
    "gn:name":"Urata Settlement",
    "gn:population":0,
    "gn:timezone":"Pacific/Fiji",
    "iso:country":"FJ",
    "name:fij_x_preferred":[
        "Urata Settlement"
    ],
    "wof:name":"Urata Settlement",
    "wof:placetype":"locality"
},
  "geometry": {"coordinates":[179.35209,-18.05252],"type":"Point"}
}