{
  "type": "Feature",
  "properties": {
    "gn:admin1_code":"03",
    "gn:admin2_code":"2197820",
    "gn:asciiname":"Batiri",
    "gn:country_code":"FJ",
    "gn:dem":11,
    "gn:feature_class":"P",
    "gn:feature_code":"PPL",
    "gn:name":"Batiri",
    "gn:population":0,
    "gn:timezone":"Pacific/Fiji",
    "iso:country":"FJ",
    "name:fij_x_preferred":[
        "Batiri"
    ],
    "name:fij_x_variant":[
        "Mbatiri"
    ],
    "wof:name":"Batiri",
    "wof:placetype":"locality"
},
  "geometry": {"coordinates":[179.03543999999999,-16.60591],"type":"Point"}
}