{
  "type": "Feature",
  "properties": {
    "gn:admin1_code":"02",
    "gn:admin2_code":"8617786",
    "gn:asciiname":"Gasele",
    "gn:country_code":"FJ",
    "gn:dem":2,
    "gn:feature_class":"P",
    "gn:feature_code":"PPL",
    "gn:name":"Gasele",
    "gn:population":0,
    "gn:timezone":"Pacific/Fiji",
    "iso:country":"FJ",
    "name:fij_x_preferred":[
        "Gasele"
    ],
    "name:und_x_variant":[
        "Naseile",
        "Ngasele"
    ],
    "wof:name":"Gasele",
    "wof:placetype":"locality"
},
  "geometry": {"coordinates":[178.30268000000001,-18.95275],"type":"Point"}
}