{
  "type": "Feature",
  "properties": {
    "gn:admin1_code":"5.0",
    "gn:asciiname":"Votua",
    "gn:country_code":"FJ",
    "gn:dem":8,
    "gn:feature_class":"P",
    "gn:feature_code":"PPL",
    "gn:name":"Votua",
    "gn:population":0,
    "gn:timezone":"Pacific/Fiji",
    "iso:country":"FJ",
    "wof:name":"Votua",
    "wof:placetype":"locality"
},
  "geometry": {"coordinates":[177.70999,-18.2084],"type":"Point"}
}