{
  "type": "Feature",
  "properties": {
    "gn:admin1_code":"01",
    "gn:admin2_code":"2198131",
    "gn:asciiname":"Qoma",
    "gn:country_code":"FJ",
    "gn:dem":12,
    "gn:feature_class":"P",
    "gn:feature_code":"PPL",
    "gn:name":"Qoma",
    "gn:population":0,
    "gn:timezone":"Pacific/Fiji",
    "iso:country":"FJ",
    "name:fij_x_preferred":[
        "Qoma"
    ],
    "name:fij_x_variant":[
        "Nggoma"
    ],
    "wof:name":"Qoma",
    "wof:placetype":"locality"
},
  "geometry": {"coordinates":[178.58376000000001,-17.63799999999999],"type":"Point"}
}