{
  "type": "Feature",
  "properties": {
    "gn:admin1_code":"3.0",
    "gn:admin2_code":"2197820.0",
    "gn:asciiname":"Valeni",
    "gn:country_code":"FJ",
    "gn:dem":8,
    "gn:feature_class":"P",
    "gn:feature_code":"PPL",
    "gn:name":"Valeni",
    "gn:population":0,
    "gn:timezone":"Pacific/Fiji",
    "iso:country":"FJ",
    "name:fij_x_preferred":[
        "Valeni"
    ],
    "wof:name":"Valeni",
    "wof:placetype":"locality"
},
  "geometry": {"coordinates":[179.12384,-16.7408],"type":"Point"}
}