{
  "type": "Feature",
  "properties": {
    "gn:admin1_code":"05",
    "gn:admin2_code":"2198946",
    "gn:asciiname":"Waimomo Settlement",
    "gn:country_code":"FJ",
    "gn:dem":82,
    "gn:feature_class":"P",
    "gn:feature_code":"PPL",
    "gn:name":"Waimomo Settlement",
    "gn:population":0,
    "gn:timezone":"Pacific/Fiji",
    "iso:country":"FJ",
    "name:fij_x_preferred":[
        "Waimomo Settlement"
    ],
    "wof:name":"Waimomo Settlement",
    "wof:placetype":"locality"
},
  "geometry": {"coordinates":[178.28286,-17.59976],"type":"Point"}
}