{
  "type": "Feature",
  "properties": {
    "gn:admin1_code":"03",
    "gn:asciiname":"Muana",
    "gn:country_code":"FJ",
    "gn:dem":-9999,
    "gn:feature_class":"P",
    "gn:feature_code":"PPL",
    "gn:name":"Muana",
    "gn:population":0,
    "gn:timezone":"Pacific/Fiji",
    "iso:country":"FJ",
    "name:fij_x_preferred":[
        "Muana"
    ],
    "wof:name":"Muana",
    "wof:placetype":"locality"
},
  "geometry": {"coordinates":[179.81666999999999,-16.51667],"type":"Point"}
}