{
  "type": "Feature",
  "properties": {
    "gn:admin1_code":"01",
    "gn:admin2_code":"2198876",
    "gn:asciiname":"Nakaile",
    "gn:country_code":"FJ",
    "gn:dem":1,
    "gn:feature_class":"P",
    "gn:feature_code":"PPL",
    "gn:name":"Nakaile",
    "gn:population":0,
    "gn:timezone":"Pacific/Fiji",
    "iso:country":"FJ",
    "name:fij_x_preferred":[
        "Nakaile"
    ],
    "wof:name":"Nakaile",
    "wof:placetype":"locality"
},
  "geometry": {"coordinates":[178.56996000000001,-18.08022],"type":"Point"}
}