{
  "type": "Feature",
  "properties": {
    "gn:admin1_code":"0.0",
    "gn:asciiname":"Tokala",
    "gn:cc2":"FJ",
    "gn:country_code":"FJ",
    "gn:dem":-9999,
    "gn:feature_class":"P",
    "gn:feature_code":"PPL",
    "gn:name":"Tokala",
    "gn:population":0,
    "gn:timezone":"Pacific/Fiji",
    "iso:country":"FJ",
    "name:und_x_variant":[
        "Tokalou",
        "Tokala"
    ],
    "wof:name":"Tokala",
    "wof:placetype":"locality"
},
  "geometry": {"coordinates":[179.78333000000001,-19.11667000000001],"type":"Point"}
}