{
  "type": "Feature",
  "properties": {
    "gn:admin1_code":"1.0",
    "gn:admin2_code":"2198131.0",
    "gn:asciiname":"Sawa",
    "gn:country_code":"FJ",
    "gn:dem":6,
    "gn:feature_class":"P",
    "gn:feature_code":"PPL",
    "gn:name":"Sawa",
    "gn:population":0,
    "gn:timezone":"Pacific/Fiji",
    "iso:country":"FJ",
    "name:fij_x_preferred":[
        "Sawa"
    ],
    "wof:name":"Sawa",
    "wof:placetype":"locality"
},
  "geometry": {"coordinates":[178.58933999999999,-17.8306],"type":"Point"}
}