{
  "type": "Feature",
  "properties": {
    "gn:admin1_code":"05",
    "gn:admin2_code":"2201984",
    "gn:asciiname":"Vunanea Settlement",
    "gn:country_code":"FJ",
    "gn:dem":99,
    "gn:feature_class":"P",
    "gn:feature_code":"PPL",
    "gn:name":"Vunanea Settlement",
    "gn:population":0,
    "gn:timezone":"Pacific/Fiji",
    "iso:country":"FJ",
    "name:fij_x_preferred":[
        "Vunanea Settlement"
    ],
    "wof:name":"Vunanea Settlement",
    "wof:placetype":"locality"
},
  "geometry": {"coordinates":[177.44779,-18.06615],"type":"Point"}
}