{
  "type": "Feature",
  "properties": {
    "gn:admin1_code":"1.0",
    "gn:asciiname":"Suvavou Village",
    "gn:country_code":"FJ",
    "gn:dem":7,
    "gn:feature_class":"P",
    "gn:feature_code":"PPL",
    "gn:name":"Suvavou Village",
    "gn:population":0,
    "gn:timezone":"Pacific/Fiji",
    "iso:country":"FJ",
    "wof:name":"Suvavou Village",
    "wof:placetype":"locality"
},
  "geometry": {"coordinates":[178.41281999999995,-18.11481],"type":"Point"}
}