{
  "type": "Feature",
  "properties": {
    "gn:admin1_code":"5.0",
    "gn:admin2_code":"2198946.0",
    "gn:asciiname":"Vitawa",
    "gn:country_code":"FJ",
    "gn:dem":18,
    "gn:feature_class":"P",
    "gn:feature_code":"PPL",
    "gn:name":"Vitawa",
    "gn:population":0,
    "gn:timezone":"Pacific/Fiji",
    "iso:country":"FJ",
    "name:fij_x_preferred":[
        "Vitawa"
    ],
    "wof:name":"Vitawa",
    "wof:placetype":"locality"
},
  "geometry": {"coordinates":[178.11126000000004,-17.37209],"type":"Point"}
}