{
  "type": "Feature",
  "properties": {
    "gn:admin1_code":"05",
    "gn:admin2_code":"2198946",
    "gn:asciiname":"Namatadamu Settlement",
    "gn:country_code":"FJ",
    "gn:dem":28,
    "gn:feature_class":"P",
    "gn:feature_code":"PPL",
    "gn:name":"Namatadamu Settlement",
    "gn:population":0,
    "gn:timezone":"Pacific/Fiji",
    "iso:country":"FJ",
    "name:fij_x_preferred":[
        "Namatadamu Settlement"
    ],
    "wof:name":"Namatadamu Settlement",
    "wof:placetype":"locality"
},
  "geometry": {"coordinates":[178.44602,-17.56635],"type":"Point"}
}