{
  "type": "Feature",
  "properties": {
    "gn:admin1_code":"03",
    "gn:admin2_code":"2197820",
    "gn:asciiname":"Nakobo",
    "gn:country_code":"FJ",
    "gn:dem":19,
    "gn:feature_class":"P",
    "gn:feature_code":"PPL",
    "gn:name":"Nakobo",
    "gn:population":0,
    "gn:timezone":"Pacific/Fiji",
    "iso:country":"FJ",
    "name:fij_x_preferred":[
        "Nakobo"
    ],
    "name:fij_x_variant":[
        "Nakombo"
    ],
    "wof:name":"Nakobo",
    "wof:placetype":"locality"
},
  "geometry": {"coordinates":[179.75588999999999,-16.72859],"type":"Point"}
}