{
  "type": "Feature",
  "properties": {
    "gn:admin1_code":"00",
    "gn:asciiname":"Hafea",
    "gn:country_code":"FJ",
    "gn:dem":11,
    "gn:feature_class":"P",
    "gn:feature_code":"PPL",
    "gn:name":"Hafea",
    "gn:population":0,
    "gn:timezone":"Pacific/Fiji",
    "iso:country":"FJ",
    "name:fij_x_preferred":[
        "Hafea"
    ],
    "name:und_x_variant":[
        "Hofvea"
    ],
    "wof:name":"Hafea",
    "wof:placetype":"locality"
},
  "geometry": {"coordinates":[177.06881000000001,-12.48171],"type":"Point"}
}