{
  "type": "Feature",
  "properties": {
    "gn:admin1_code":"01",
    "gn:admin2_code":"2198411",
    "gn:asciiname":"Lepanoni Settlement",
    "gn:country_code":"FJ",
    "gn:dem":8,
    "gn:feature_class":"P",
    "gn:feature_code":"PPL",
    "gn:name":"Lepanoni Settlement",
    "gn:population":0,
    "gn:timezone":"Pacific/Fiji",
    "iso:country":"FJ",
    "name:fij_x_preferred":[
        "Lepanoni Settlement"
    ],
    "wof:name":"Lepanoni Settlement",
    "wof:placetype":"locality"
},
  "geometry": {"coordinates":[178.05489,-18.25736],"type":"Point"}
}