{
  "type": "Feature",
  "properties": {
    "gn:admin1_code":"03",
    "gn:admin2_code":"2203875",
    "gn:asciiname":"Ruaruavesi Settlement",
    "gn:country_code":"FJ",
    "gn:dem":48,
    "gn:feature_class":"P",
    "gn:feature_code":"PPL",
    "gn:name":"Ruaruavesi Settlement",
    "gn:population":0,
    "gn:timezone":"Pacific/Fiji",
    "iso:country":"FJ",
    "name:fij_x_preferred":[
        "Ruaruavesi Settlement"
    ],
    "wof:name":"Ruaruavesi Settlement",
    "wof:placetype":"locality"
},
  "geometry": {"coordinates":[178.92927,-16.48941],"type":"Point"}
}