{
  "type": "Feature",
  "properties": {
    "gn:admin1_code":"01",
    "gn:admin2_code":"2198411",
    "gn:asciiname":"Naqesa Settlement",
    "gn:country_code":"FJ",
    "gn:dem":35,
    "gn:feature_class":"P",
    "gn:feature_code":"PPL",
    "gn:name":"Naqesa Settlement",
    "gn:population":0,
    "gn:timezone":"Pacific/Fiji",
    "iso:country":"FJ",
    "name:fij_x_preferred":[
        "Naqesa Settlement"
    ],
    "wof:name":"Naqesa Settlement",
    "wof:placetype":"locality"
},
  "geometry": {"coordinates":[178.05316999999999,-18.09285],"type":"Point"}
}