{
  "type": "Feature",
  "properties": {
    "gn:admin1_code":"05",
    "gn:admin2_code":"2198946",
    "gn:asciiname":"Naboutolu",
    "gn:country_code":"FJ",
    "gn:dem":39,
    "gn:feature_class":"P",
    "gn:feature_code":"PPL",
    "gn:name":"Naboutolu",
    "gn:population":0,
    "gn:timezone":"Pacific/Fiji",
    "iso:country":"FJ",
    "name:fij_x_preferred":[
        "Naboutolu"
    ],
    "wof:name":"Naboutolu",
    "wof:placetype":"locality"
},
  "geometry": {"coordinates":[178.23723000000001,-17.40064],"type":"Point"}
}