{
  "type": "Feature",
  "properties": {
    "gn:admin1_code":"00",
    "gn:asciiname":"Lovoni",
    "gn:country_code":"FJ",
    "gn:dem":33,
    "gn:feature_class":"P",
    "gn:feature_code":"PPL",
    "gn:name":"Lovoni",
    "gn:population":0,
    "gn:timezone":"Pacific/Fiji",
    "iso:country":"FJ",
    "name:und_x_variant":[
        "Levoni",
        "Lovoni"
    ],
    "wof:name":"Lovoni",
    "wof:placetype":"locality"
},
  "geometry": {"coordinates":[178.79203000000001,-17.6905],"type":"Point"}
}