{
  "type": "Feature",
  "properties": {
    "gn:admin1_code":"3.0",
    "gn:admin2_code":"2203875.0",
    "gn:asciiname":"Wailevu",
    "gn:country_code":"FJ",
    "gn:dem":1,
    "gn:feature_class":"P",
    "gn:feature_code":"PPL",
    "gn:name":"Wailevu",
    "gn:population":0,
    "gn:timezone":"Pacific/Fiji",
    "iso:country":"FJ",
    "name:fij_x_preferred":[
        "Wailevu"
    ],
    "wof:name":"Wailevu",
    "wof:placetype":"locality"
},
  "geometry": {"coordinates":[179.32748000000001,-16.43216],"type":"Point"}
}