{
  "type": "Feature",
  "properties": {
    "gn:admin1_code":"05",
    "gn:admin2_code":"2198946",
    "gn:asciiname":"Waidele Settlement",
    "gn:country_code":"FJ",
    "gn:dem":225,
    "gn:feature_class":"P",
    "gn:feature_code":"PPL",
    "gn:name":"Waidele Settlement",
    "gn:population":0,
    "gn:timezone":"Pacific/Fiji",
    "iso:country":"FJ",
    "name:fij_x_preferred":[
        "Waidele Settlement"
    ],
    "wof:name":"Waidele Settlement",
    "wof:placetype":"locality"
},
  "geometry": {"coordinates":[178.32527999999999,-17.49031],"type":"Point"}
}