{
  "type": "Feature",
  "properties": {
    "gn:admin1_code":"02",
    "gn:admin2_code":"2204318",
    "gn:asciiname":"Malawai",
    "gn:country_code":"FJ",
    "gn:dem":18,
    "gn:feature_class":"P",
    "gn:feature_code":"PPL",
    "gn:name":"Malawai",
    "gn:population":0,
    "gn:timezone":"Pacific/Fiji",
    "iso:country":"FJ",
    "name:fij_x_preferred":[
        "Malawai"
    ],
    "wof:name":"Malawai",
    "wof:placetype":"locality"
},
  "geometry": {"coordinates":[179.33940000000001,-18.00228],"type":"Point"}
}