{
  "type": "Feature",
  "properties": {
    "gn:admin1_code":"05",
    "gn:admin2_code":"2198946",
    "gn:asciiname":"Nukulau",
    "gn:country_code":"FJ",
    "gn:dem":343,
    "gn:feature_class":"P",
    "gn:feature_code":"PPL",
    "gn:name":"Nukulau",
    "gn:population":0,
    "gn:timezone":"Pacific/Fiji",
    "iso:country":"FJ",
    "name:ceb_x_preferred":[
        "Nukulau Island"
    ],
    "name:ces_x_preferred":[
        "Nukulau"
    ],
    "name:deu_x_preferred":[
        "Nukulau"
    ],
    "name:hif_x_preferred":[
        "Nukulau"
    ],
    "name:rus_x_preferred":[
        "\u041d\u0443\u043a\u0443\u043b\u0430\u0443"
    ],
    "name:swe_x_preferred":[
        "Nukulau Island"
    ],
    "name:und_x_variant":[
        "Nokulau",
        "Nukulau"
    ],
    "name:zho_x_preferred":[
        "\u52aa\u5eab\u52de\u5cf6"
    ],
    "wof:name":"Nukulau",
    "wof:placetype":"locality"
},
  "geometry": {"coordinates":[178.12401,-17.65249],"type":"Point"}
}