{
  "type": "Feature",
  "properties": {
    "gn:admin1_code":"05",
    "gn:admin2_code":"2201984",
    "gn:asciiname":"Balenabelo",
    "gn:country_code":"FJ",
    "gn:dem":17,
    "gn:feature_class":"P",
    "gn:feature_code":"PPL",
    "gn:name":"Balenabelo",
    "gn:population":0,
    "gn:timezone":"Pacific/Fiji",
    "iso:country":"FJ",
    "name:fij_x_preferred":[
        "Balenabelo"
    ],
    "name:und_x_variant":[
        "Mbalenambelo"
    ],
    "wof:name":"Balenabelo",
    "wof:placetype":"locality"
},
  "geometry": {"coordinates":[177.62191000000001,-18.16459],"type":"Point"}
}