{
  "type": "Feature",
  "properties": {
    "gn:admin1_code":"01",
    "gn:admin2_code":"2203150",
    "gn:asciiname":"Navurevure",
    "gn:country_code":"FJ",
    "gn:dem":26,
    "gn:feature_class":"P",
    "gn:feature_code":"PPL",
    "gn:name":"Navurevure",
    "gn:population":0,
    "gn:timezone":"Pacific/Fiji",
    "iso:country":"FJ",
    "name:fij_x_preferred":[
        "Navurevure"
    ],
    "wof:name":"Navurevure",
    "wof:placetype":"locality"
},
  "geometry": {"coordinates":[178.30626999999996,-17.99146],"type":"Point"}
}