{
  "type": "Feature",
  "properties": {
    "gn:admin1_code":"02",
    "gn:admin2_code":"2204318",
    "gn:asciiname":"Qarani",
    "gn:country_code":"FJ",
    "gn:dem":-1,
    "gn:feature_class":"P",
    "gn:feature_code":"PPL",
    "gn:name":"Qarani",
    "gn:population":0,
    "gn:timezone":"Pacific/Fiji",
    "iso:country":"FJ",
    "name:und_x_variant":[
        "Loloa",
        "Qarani",
        "Nggarani"
    ],
    "wof:name":"Qarani",
    "wof:placetype":"locality"
},
  "geometry": {"coordinates":[179.26981999999995,-17.94697],"type":"Point"}
}