{
  "type": "Feature",
  "properties": {
    "gn:admin1_code":"01",
    "gn:admin2_code":"2203150",
    "gn:asciiname":"Baulevu Settlement",
    "gn:country_code":"FJ",
    "gn:dem":21,
    "gn:feature_class":"P",
    "gn:feature_code":"PPL",
    "gn:name":"Baulevu Settlement",
    "gn:population":0,
    "gn:timezone":"Pacific/Fiji",
    "iso:country":"FJ",
    "name:fij_x_preferred":[
        "Baulevu Settlement"
    ],
    "name:fij_x_variant":[
        "Mbaulevu"
    ],
    "wof:name":"Baulevu Settlement",
    "wof:placetype":"locality"
},
  "geometry": {"coordinates":[178.43507,-17.96864],"type":"Point"}
}