{
  "type": "Feature",
  "properties": {
    "gn:admin1_code":"02",
    "gn:admin2_code":"2204318",
    "gn:asciiname":"Daku",
    "gn:country_code":"FJ",
    "gn:dem":9,
    "gn:feature_class":"P",
    "gn:feature_code":"PPL",
    "gn:name":"Daku",
    "gn:population":0,
    "gn:timezone":"Pacific/Fiji",
    "iso:country":"FJ",
    "name:fij_x_preferred":[
        "Daku"
    ],
    "name:fij_x_variant":[
        "Ndaku"
    ],
    "wof:name":"Daku",
    "wof:placetype":"locality"
},
  "geometry": {"coordinates":[178.77203,-17.77761],"type":"Point"}
}