{
  "type": "Feature",
  "properties": {
    "gn:admin1_code":"4.0",
    "gn:asciiname":"Saolei",
    "gn:country_code":"FJ",
    "gn:dem":-9999,
    "gn:feature_class":"P",
    "gn:feature_code":"PPL",
    "gn:name":"Saolei",
    "gn:population":0,
    "gn:timezone":"Pacific/Fiji",
    "iso:country":"FJ",
    "name:fij_x_preferred":[
        "Saolei"
    ],
    "wof:name":"Saolei",
    "wof:placetype":"locality"
},
  "geometry": {"coordinates":[177.05998,-12.51897],"type":"Point"}
}