{
  "type": "Feature",
  "properties": {
    "gn:admin1_code":"01",
    "gn:admin2_code":"2203150",
    "gn:asciiname":"Narokorokoyawa",
    "gn:country_code":"FJ",
    "gn:dem":197,
    "gn:feature_class":"P",
    "gn:feature_code":"PPL",
    "gn:name":"Narokorokoyawa",
    "gn:population":0,
    "gn:timezone":"Pacific/Fiji",
    "iso:country":"FJ",
    "name:fij_x_preferred":[
        "Narokorokoyawa"
    ],
    "wof:name":"Narokorokoyawa",
    "wof:placetype":"locality"
},
  "geometry": {"coordinates":[178.10418999999999,-17.8514],"type":"Point"}
}