{
  "type": "Feature",
  "properties": {
    "gn:admin1_code":"03",
    "gn:asciiname":"Nakarambo",
    "gn:cc2":"FJ",
    "gn:country_code":"FJ",
    "gn:dem":141,
    "gn:feature_class":"P",
    "gn:feature_code":"PPL",
    "gn:name":"Nakarambo",
    "gn:population":0,
    "gn:timezone":"Pacific/Fiji",
    "iso:country":"FJ",
    "name:und_x_variant":[
        "Nakarabo",
        "Nakarambo"
    ],
    "wof:name":"Nakarambo",
    "wof:placetype":"locality"
},
  "geometry": {"coordinates":[179.56666999999999,-16.55],"type":"Point"}
}