{
  "type": "Feature",
  "properties": {
    "gn:admin1_code":"05",
    "gn:admin2_code":"2198946",
    "gn:asciiname":"Bona Settlement",
    "gn:country_code":"FJ",
    "gn:dem":11,
    "gn:feature_class":"P",
    "gn:feature_code":"PPL",
    "gn:name":"Bona Settlement",
    "gn:population":0,
    "gn:timezone":"Pacific/Fiji",
    "iso:country":"FJ",
    "name:fij_x_preferred":[
        "Bona Settlement"
    ],
    "wof:name":"Bona Settlement",
    "wof:placetype":"locality"
},
  "geometry": {"coordinates":[178.25946000000005,-17.4632],"type":"Point"}
}