{
  "type": "Feature",
  "properties": {
    "gn:admin1_code":"05",
    "gn:admin2_code":"2201984",
    "gn:asciiname":"Lomolomo Settlement",
    "gn:country_code":"FJ",
    "gn:dem":86,
    "gn:feature_class":"P",
    "gn:feature_code":"PPL",
    "gn:name":"Lomolomo Settlement",
    "gn:population":0,
    "gn:timezone":"Pacific/Fiji",
    "iso:country":"FJ",
    "name:fij_x_preferred":[
        "Lomolomo Settlement"
    ],
    "wof:name":"Lomolomo Settlement",
    "wof:placetype":"locality"
},
  "geometry": {"coordinates":[177.72793999999999,-17.99092000000001],"type":"Point"}
}