{
  "type": "Feature",
  "properties": {
    "gn:admin1_code":"05",
    "gn:admin2_code":"2198946",
    "gn:asciiname":"Rakiraki",
    "gn:country_code":"FJ",
    "gn:dem":8,
    "gn:feature_class":"P",
    "gn:feature_code":"PPL",
    "gn:name":"Rakiraki",
    "gn:population":0,
    "gn:timezone":"Pacific/Fiji",
    "iso:country":"FJ",
    "name:und_x_variant":[
        "Penang",
        "Rakiraki"
    ],
    "wof:name":"Rakiraki",
    "wof:placetype":"locality"
},
  "geometry": {"coordinates":[178.16072,-17.36388],"type":"Point"}
}