{
  "type": "Feature",
  "properties": {
    "gn:admin1_code":"02",
    "gn:admin2_code":"8617786",
    "gn:asciiname":"Naivimagimagi Settlement",
    "gn:country_code":"FJ",
    "gn:dem":25,
    "gn:feature_class":"P",
    "gn:feature_code":"PPL",
    "gn:name":"Naivimagimagi Settlement",
    "gn:population":0,
    "gn:timezone":"Pacific/Fiji",
    "iso:country":"FJ",
    "name:fij_x_preferred":[
        "Naivimagimagi Settlement"
    ],
    "name:fij_x_variant":[
        "Naivi Mangimangi"
    ],
    "wof:name":"Naivimagimagi Settlement",
    "wof:placetype":"locality"
},
  "geometry": {"coordinates":[178.40520000000001,-19.03452],"type":"Point"}
}