{
  "type": "Feature",
  "properties": {
    "gn:admin1_code":"03",
    "gn:admin2_code":"2203651",
    "gn:asciiname":"Bualailai Settlement",
    "gn:country_code":"FJ",
    "gn:dem":11,
    "gn:feature_class":"P",
    "gn:feature_code":"PPL",
    "gn:name":"Bualailai Settlement",
    "gn:population":0,
    "gn:timezone":"Pacific/Fiji",
    "iso:country":"FJ",
    "name:fij_x_preferred":[
        "Bualailai Settlement"
    ],
    "wof:name":"Bualailai Settlement",
    "wof:placetype":"locality"
},
  "geometry": {"coordinates":[178.63856999999999,-16.67232000000001],"type":"Point"}
}