{
  "type": "Feature",
  "properties": {
    "iso:country":"FJ",
    "qs:gn_pop":0,
    "qs:name":"Samambula",
    "qs:name_adm0":"Fiji",
    "qs:name_adm1":"Central",
    "qs:photos":190,
    "qs:photos_1k":39,
    "qs:photos_9k":1,
    "qs:photos_9r":4,
    "qs:photos_all":190,
    "qs:photos_sr":4,
    "qs:placetype":"Suburb",
    "qs:pop_sr":"0",
    "qs:woe_adm0":23424813,
    "wof:name":"Samambula",
    "wof:placetype":"neighbourhood"
},
  "geometry": {"coordinates":[178.44440399999999,-18.108084],"type":"Point"}
}