{
  "type": "Feature",
  "properties": {
    "gn:admin1_code":"02",
    "gn:admin2_code":"8617786",
    "gn:asciiname":"Matari Settlement",
    "gn:country_code":"FJ",
    "gn:dem":8,
    "gn:feature_class":"P",
    "gn:feature_code":"PPL",
    "gn:name":"Matari Settlement",
    "gn:population":0,
    "gn:timezone":"Pacific/Fiji",
    "iso:country":"FJ",
    "name:fij_x_preferred":[
        "Matari Settlement"
    ],
    "wof:name":"Matari Settlement",
    "wof:placetype":"locality"
},
  "geometry": {"coordinates":[178.32986,-18.9335],"type":"Point"}
}