{
  "type": "Feature",
  "properties": {
    "gn:admin1_code":"05",
    "gn:admin2_code":"2203798",
    "gn:asciiname":"Nabuna Set",
    "gn:country_code":"FJ",
    "gn:dem":9,
    "gn:feature_class":"P",
    "gn:feature_code":"PPL",
    "gn:name":"Nabuna Set",
    "gn:population":0,
    "gn:timezone":"Pacific/Fiji",
    "iso:country":"FJ",
    "name:fij_x_preferred":[
        "Nabuna Set"
    ],
    "name:und_x_variant":[
        "Vanua-kula",
        "Nambuna"
    ],
    "wof:name":"Nabuna Set",
    "wof:placetype":"locality"
},
  "geometry": {"coordinates":[177.87108999999995,-17.43732],"type":"Point"}
}