{
  "type": "Feature",
  "properties": {
    "gn:admin1_code":"02",
    "gn:admin2_code":"4036132",
    "gn:asciiname":"Namalata",
    "gn:country_code":"FJ",
    "gn:dem":20,
    "gn:feature_class":"P",
    "gn:feature_code":"PPL",
    "gn:name":"Namalata",
    "gn:population":0,
    "gn:timezone":"Pacific/Fiji",
    "iso:country":"FJ",
    "name:fij_x_preferred":[
        "Namalata"
    ],
    "wof:name":"Namalata",
    "wof:placetype":"locality"
},
  "geometry": {"coordinates":[-178.99011000000004,-17.32866],"type":"Point"}
}