{
  "type": "Feature",
  "properties": {
    "gn:admin1_code":"00",
    "gn:asciiname":"Drue",
    "gn:country_code":"FJ",
    "gn:dem":21,
    "gn:feature_class":"P",
    "gn:feature_code":"PPL",
    "gn:name":"Drue",
    "gn:population":0,
    "gn:timezone":"Pacific/Fiji",
    "iso:country":"FJ",
    "name:eng_x_preferred":[
        "Drue"
    ],
    "wof:name":"Drue",
    "wof:placetype":"locality"
},
  "geometry": {"coordinates":[178.16141999999999,-19.00427],"type":"Point"}
}