{
  "type": "Feature",
  "properties": {
    "gn:admin1_code":"01",
    "gn:admin2_code":"2198876",
    "gn:asciiname":"Wainidinu",
    "gn:country_code":"FJ",
    "gn:dem":20,
    "gn:feature_class":"P",
    "gn:feature_code":"PPL",
    "gn:name":"Wainidinu",
    "gn:population":0,
    "gn:timezone":"Pacific/Fiji",
    "iso:country":"FJ",
    "name:fij_x_preferred":[
        "Wainidinu"
    ],
    "wof:name":"Wainidinu",
    "wof:placetype":"locality"
},
  "geometry": {"coordinates":[178.42006999999995,-18.11104],"type":"Point"}
}