{
  "type": "Feature",
  "properties": {
    "gn:admin1_code":"1.0",
    "gn:admin2_code":"2198411.0",
    "gn:asciiname":"Culanuku",
    "gn:country_code":"FJ",
    "gn:dem":7,
    "gn:feature_class":"P",
    "gn:feature_code":"PPL",
    "gn:name":"Culanuku",
    "gn:population":0,
    "gn:timezone":"Pacific/Fiji",
    "iso:country":"FJ",
    "name:fij_x_preferred":[
        "Culanuku"
    ],
    "name:und_x_variant":[
        "Thulanuku"
    ],
    "wof:name":"Culanuku",
    "wof:placetype":"locality"
},
  "geometry": {"coordinates":[177.98665,-18.26741],"type":"Point"}
}