{
  "type": "Feature",
  "properties": {
    "gn:admin1_code":"5.0",
    "gn:asciiname":"Yavulo",
    "gn:country_code":"FJ",
    "gn:dem":9,
    "gn:feature_class":"P",
    "gn:feature_code":"PPL",
    "gn:name":"Yavulo",
    "gn:population":0,
    "gn:timezone":"Pacific/Fiji",
    "iso:country":"FJ",
    "name:fij_x_preferred":[
        "Yavulo"
    ],
    "wof:name":"Yavulo",
    "wof:placetype":"locality"
},
  "geometry": {"coordinates":[177.51667,-18.15],"type":"Point"}
}