{
  "type": "Feature",
  "properties": {
    "gn:admin1_code":"01",
    "gn:admin2_code":"2203150",
    "gn:asciiname":"Lutu",
    "gn:country_code":"FJ",
    "gn:dem":126,
    "gn:feature_class":"P",
    "gn:feature_code":"PPL",
    "gn:name":"Lutu",
    "gn:population":0,
    "gn:timezone":"Pacific/Fiji",
    "iso:country":"FJ",
    "name:fij_x_preferred":[
        "Lutu"
    ],
    "wof:name":"Lutu",
    "wof:placetype":"locality"
},
  "geometry": {"coordinates":[178.11346,-17.80315],"type":"Point"}
}