{
  "type": "Feature",
  "properties": {
    "gn:admin1_code":"01",
    "gn:admin2_code":"2203150",
    "gn:asciiname":"Delaitoga",
    "gn:country_code":"FJ",
    "gn:dem":24,
    "gn:feature_class":"P",
    "gn:feature_code":"PPL",
    "gn:name":"Delaitoga",
    "gn:population":0,
    "gn:timezone":"Pacific/Fiji",
    "iso:country":"FJ",
    "name:fij_x_preferred":[
        "Ndelaitonga"
    ],
    "name:fij_x_variant":[
        "Delaitoga"
    ],
    "wof:name":"Delaitoga",
    "wof:placetype":"locality"
},
  "geometry": {"coordinates":[178.31253000000001,-17.82623],"type":"Point"}
}