{
  "type": "Feature",
  "properties": {
    "gn:admin1_code":"05",
    "gn:admin2_code":"2203798",
    "gn:asciiname":"Soweri Settlement",
    "gn:country_code":"FJ",
    "gn:dem":20,
    "gn:feature_class":"P",
    "gn:feature_code":"PPL",
    "gn:name":"Soweri Settlement",
    "gn:population":0,
    "gn:timezone":"Pacific/Fiji",
    "iso:country":"FJ",
    "name:fij_x_preferred":[
        "Soweri Settlement"
    ],
    "wof:name":"Soweri Settlement",
    "wof:placetype":"locality"
},
  "geometry": {"coordinates":[177.69168999999999,-17.56549],"type":"Point"}
}