{
  "type": "Feature",
  "properties": {
    "gn:admin1_code":"01",
    "gn:admin2_code":"2198411",
    "gn:asciiname":"Tubarua Settlement",
    "gn:country_code":"FJ",
    "gn:dem":28,
    "gn:feature_class":"P",
    "gn:feature_code":"PPL",
    "gn:name":"Tubarua Settlement",
    "gn:population":0,
    "gn:timezone":"Pacific/Fiji",
    "iso:country":"FJ",
    "name:fij_x_preferred":[
        "Tubarua Settlement"
    ],
    "wof:name":"Tubarua Settlement",
    "wof:placetype":"locality"
},
  "geometry": {"coordinates":[177.99934999999999,-18.22541],"type":"Point"}
}