{
  "type": "Feature",
  "properties": {
    "gn:admin1_code":"05",
    "gn:admin2_code":"2203798",
    "gn:asciiname":"Namara",
    "gn:country_code":"FJ",
    "gn:dem":22,
    "gn:feature_class":"P",
    "gn:feature_code":"PPL",
    "gn:name":"Namara",
    "gn:population":0,
    "gn:timezone":"Pacific/Fiji",
    "iso:country":"FJ",
    "name:fij_x_preferred":[
        "Namara"
    ],
    "wof:name":"Namara",
    "wof:placetype":"locality"
},
  "geometry": {"coordinates":[177.13952,-17.3525],"type":"Point"}
}