{
  "type": "Feature",
  "properties": {
    "gn:admin1_code":"03",
    "gn:admin2_code":"2203875",
    "gn:asciiname":"Natekateka Settlement",
    "gn:country_code":"FJ",
    "gn:dem":15,
    "gn:feature_class":"P",
    "gn:feature_code":"PPL",
    "gn:name":"Natekateka Settlement",
    "gn:population":0,
    "gn:timezone":"Pacific/Fiji",
    "iso:country":"FJ",
    "name:fij_x_preferred":[
        "Natekateka Settlement"
    ],
    "wof:name":"Natekateka Settlement",
    "wof:placetype":"locality"
},
  "geometry": {"coordinates":[178.99221,-16.62454],"type":"Point"}
}