{
  "type": "Feature",
  "properties": {
    "gn:admin1_code":"05",
    "gn:admin2_code":"2201984",
    "gn:asciiname":"Navutu",
    "gn:country_code":"FJ",
    "gn:dem":14,
    "gn:feature_class":"P",
    "gn:feature_code":"PPL",
    "gn:name":"Navutu",
    "gn:population":0,
    "gn:timezone":"Pacific/Fiji",
    "iso:country":"FJ",
    "name:fij_x_preferred":[
        "Navutu"
    ],
    "wof:name":"Navutu",
    "wof:placetype":"locality"
},
  "geometry": {"coordinates":[177.3262,-18.01118],"type":"Point"}
}