{
  "type": "Feature",
  "properties": {
    "gn:admin1_code":"3.0",
    "gn:admin2_code":"2203875.0",
    "gn:asciiname":"Salevukoso",
    "gn:country_code":"FJ",
    "gn:dem":0,
    "gn:feature_class":"P",
    "gn:feature_code":"PPL",
    "gn:name":"Salevukoso",
    "gn:population":0,
    "gn:timezone":"Pacific/Fiji",
    "iso:country":"FJ",
    "name:fij_x_preferred":[
        "Salevukoso"
    ],
    "wof:name":"Salevukoso",
    "wof:placetype":"locality"
},
  "geometry": {"coordinates":[179.61278999999999,-16.18644],"type":"Point"}
}