{
  "type": "Feature",
  "properties": {
    "gn:admin1_code":"1.0",
    "gn:admin2_code":"2198411.0",
    "gn:asciiname":"Waibogi",
    "gn:country_code":"FJ",
    "gn:dem":64,
    "gn:feature_class":"P",
    "gn:feature_code":"PPL",
    "gn:name":"Waibogi",
    "gn:population":0,
    "gn:timezone":"Pacific/Fiji",
    "iso:country":"FJ",
    "name:fij_x_preferred":[
        "Waibogi"
    ],
    "name:fij_x_variant":[
        "Waimbongi"
    ],
    "wof:name":"Waibogi",
    "wof:placetype":"locality"
},
  "geometry": {"coordinates":[178.00928999999999,-18.1168],"type":"Point"}
}