{
  "type": "Feature",
  "properties": {
    "gn:admin1_code":"01",
    "gn:admin2_code":"2198131",
    "gn:asciiname":"Korolevu",
    "gn:country_code":"FJ",
    "gn:dem":18,
    "gn:feature_class":"P",
    "gn:feature_code":"PPL",
    "gn:name":"Korolevu",
    "gn:population":0,
    "gn:timezone":"Pacific/Fiji",
    "iso:country":"FJ",
    "name:und_x_variant":[
        "Nakorolevu",
        "Korolevu"
    ],
    "wof:name":"Korolevu",
    "wof:placetype":"locality"
},
  "geometry": {"coordinates":[178.58918,-17.94422],"type":"Point"}
}