{
  "type": "Feature",
  "properties": {
    "gn:admin1_code":"02",
    "gn:admin2_code":"8617786",
    "gn:asciiname":"Nukudu Settlement",
    "gn:country_code":"FJ",
    "gn:dem":11,
    "gn:feature_class":"P",
    "gn:feature_code":"PPL",
    "gn:name":"Nukudu Settlement",
    "gn:population":0,
    "gn:timezone":"Pacific/Fiji",
    "iso:country":"FJ",
    "name:fij_x_preferred":[
        "Nukudu Settlement"
    ],
    "wof:name":"Nukudu Settlement",
    "wof:placetype":"locality"
},
  "geometry": {"coordinates":[178.27333000000004,-18.96965],"type":"Point"}
}