{
  "type": "Feature",
  "properties": {
    "gn:admin1_code":"01",
    "gn:admin2_code":"2202182",
    "gn:asciiname":"Naqarawai",
    "gn:country_code":"FJ",
    "gn:dem":224,
    "gn:feature_class":"P",
    "gn:feature_code":"PPL",
    "gn:name":"Naqarawai",
    "gn:population":0,
    "gn:timezone":"Pacific/Fiji",
    "iso:country":"FJ",
    "name:fij_x_preferred":[
        "Naqarawai"
    ],
    "name:fij_x_variant":[
        "Nanggarawai"
    ],
    "wof:name":"Naqarawai",
    "wof:placetype":"locality"
},
  "geometry": {"coordinates":[178.07821000000001,-17.98142],"type":"Point"}
}