{
  "type": "Feature",
  "properties": {
    "gn:admin1_code":"05",
    "gn:admin2_code":"2203798",
    "gn:asciiname":"Old Lololo Village",
    "gn:country_code":"FJ",
    "gn:dem":113,
    "gn:feature_class":"P",
    "gn:feature_code":"PPL",
    "gn:name":"Old Lololo Village",
    "gn:population":0,
    "gn:timezone":"Pacific/Fiji",
    "iso:country":"FJ",
    "name:fij_x_preferred":[
        "Old Lololo Village"
    ],
    "wof:name":"Old Lololo Village",
    "wof:placetype":"locality"
},
  "geometry": {"coordinates":[177.58073000000005,-17.56976],"type":"Point"}
}