{
  "type": "Feature",
  "properties": {
    "gn:admin1_code":"03",
    "gn:asciiname":"Navetau",
    "gn:cc2":"FJ",
    "gn:country_code":"FJ",
    "gn:dem":89,
    "gn:feature_class":"P",
    "gn:feature_code":"PPL",
    "gn:name":"Navetau",
    "gn:population":0,
    "gn:timezone":"Pacific/Fiji",
    "iso:country":"FJ",
    "name:und_x_variant":[
        "Vatuloa",
        "Navetau"
    ],
    "wof:name":"Navetau",
    "wof:placetype":"locality"
},
  "geometry": {"coordinates":[179.68333000000001,-16.48333],"type":"Point"}
}