{
  "type": "Feature",
  "properties": {
    "gn:admin1_code":"03",
    "gn:admin2_code":"2203875",
    "gn:asciiname":"Lidiasiga",
    "gn:country_code":"FJ",
    "gn:dem":1,
    "gn:feature_class":"P",
    "gn:feature_code":"PPL",
    "gn:name":"Lidiasiga",
    "gn:population":0,
    "gn:timezone":"Pacific/Fiji",
    "iso:country":"FJ",
    "name:fij_x_preferred":[
        "Lidiasiga"
    ],
    "name:fij_x_variant":[
        "Lindiasinga"
    ],
    "wof:name":"Lidiasiga",
    "wof:placetype":"locality"
},
  "geometry": {"coordinates":[179.34998999999999,-16.35321],"type":"Point"}
}