{
  "type": "Feature",
  "properties": {
    "gn:admin1_code":"5.0",
    "gn:admin2_code":"2203798.0",
    "gn:asciiname":"Sasa",
    "gn:country_code":"FJ",
    "gn:dem":10,
    "gn:feature_class":"P",
    "gn:feature_code":"PPL",
    "gn:name":"Sasa",
    "gn:population":0,
    "gn:timezone":"Pacific/Fiji",
    "iso:country":"FJ",
    "name:ara_x_preferred":[
        "\u0633\u0639\u0633\u0639"
    ],
    "name:ceb_x_preferred":[
        "Sasa"
    ],
    "name:deu_x_preferred":[
        "Sasa"
    ],
    "name:epo_x_preferred":[
        "Sasa"
    ],
    "name:fij_x_preferred":[
        "Sasa"
    ],
    "name:fra_x_preferred":[
        "Sasa"
    ],
    "name:hrv_x_preferred":[
        "Sasa"
    ],
    "name:ita_x_preferred":[
        "Sasa"
    ],
    "name:jpn_x_preferred":[
        "\u30b5\u30b5"
    ],
    "name:sqi_x_preferred":[
        "Sasa"
    ],
    "name:srp_x_preferred":[
        "\u0421\u0430\u0441\u0430"
    ],
    "name:swe_x_preferred":[
        "Sasa"
    ],
    "wof:name":"Sasa",
    "wof:placetype":"locality"
},
  "geometry": {"coordinates":[177.70744999999999,-17.4869],"type":"Point"}
}