{
  "type": "Feature",
  "properties": {
    "gn:admin1_code":"2.0",
    "gn:admin2_code":"8617786.0",
    "gn:asciiname":"Tavuki",
    "gn:country_code":"FJ",
    "gn:dem":2,
    "gn:feature_class":"P",
    "gn:feature_code":"PPL",
    "gn:name":"Tavuki",
    "gn:population":0,
    "gn:timezone":"Pacific/Fiji",
    "iso:country":"FJ",
    "name:und_x_variant":[
        "Tavuka",
        "Tavuki"
    ],
    "wof:name":"Tavuki",
    "wof:placetype":"locality"
},
  "geometry": {"coordinates":[178.10787999999999,-19.07736],"type":"Point"}
}