{
  "type": "Feature",
  "properties": {
    "gn:admin1_code":"00",
    "gn:asciiname":"Naroi",
    "gn:country_code":"FJ",
    "gn:dem":32,
    "gn:feature_class":"P",
    "gn:feature_code":"PPL",
    "gn:name":"Naroi",
    "gn:population":0,
    "gn:timezone":"Pacific/Fiji",
    "iso:country":"FJ",
    "name:deu_x_preferred":[
        "Naroi"
    ],
    "name:fij_x_preferred":[
        "Naroi"
    ],
    "wof:name":"Naroi",
    "wof:placetype":"locality"
},
  "geometry": {"coordinates":[179.94999999999999,-18.56667],"type":"Point"}
}