{
  "type": "Feature",
  "properties": {
    "gn:admin1_code":"1.0",
    "gn:admin2_code":"2198131.0",
    "gn:asciiname":"Vaturua",
    "gn:country_code":"FJ",
    "gn:dem":7,
    "gn:feature_class":"P",
    "gn:feature_code":"PPL",
    "gn:name":"Vaturua",
    "gn:population":0,
    "gn:timezone":"Pacific/Fiji",
    "iso:country":"FJ",
    "name:fij_x_preferred":[
        "Vaturua"
    ],
    "wof:name":"Vaturua",
    "wof:placetype":"locality"
},
  "geometry": {"coordinates":[178.6052,-18.0728],"type":"Point"}
}