{
  "type": "Feature",
  "properties": {
    "gn:admin1_code":"03",
    "gn:admin2_code":"2197820",
    "gn:asciiname":"Nadilo",
    "gn:country_code":"FJ",
    "gn:dem":17,
    "gn:feature_class":"P",
    "gn:feature_code":"PPL",
    "gn:name":"Nadilo",
    "gn:population":0,
    "gn:timezone":"Pacific/Fiji",
    "iso:country":"FJ",
    "name:fij_x_preferred":[
        "Nadilo"
    ],
    "name:und_x_variant":[
        "Ndilo",
        "Nandilo"
    ],
    "wof:name":"Nadilo",
    "wof:placetype":"locality"
},
  "geometry": {"coordinates":[-179.77923000000001,-16.78902],"type":"Point"}
}