{
  "type": "Feature",
  "properties": {
    "gn:admin1_code":"02",
    "gn:admin2_code":"8617786",
    "gn:asciiname":"Naqalotu",
    "gn:country_code":"FJ",
    "gn:dem":11,
    "gn:feature_class":"P",
    "gn:feature_code":"PPL",
    "gn:name":"Naqalotu",
    "gn:population":0,
    "gn:timezone":"Pacific/Fiji",
    "iso:country":"FJ",
    "name:fij_x_preferred":[
        "Naqalotu"
    ],
    "name:fij_x_variant":[
        "Nanggalotu"
    ],
    "wof:name":"Naqalotu",
    "wof:placetype":"locality"
},
  "geometry": {"coordinates":[178.04092,-19.07412],"type":"Point"}
}