{
  "type": "Feature",
  "properties": {
    "gn:admin1_code":"02",
    "gn:admin2_code":"8617786",
    "gn:asciiname":"Nakaugasele",
    "gn:country_code":"FJ",
    "gn:dem":11,
    "gn:feature_class":"P",
    "gn:feature_code":"PPL",
    "gn:name":"Nakaugasele",
    "gn:population":0,
    "gn:timezone":"Pacific/Fiji",
    "iso:country":"FJ",
    "name:fij_x_preferred":[
        "Nakaugasele"
    ],
    "name:fij_x_variant":[
        "Nakaungasele"
    ],
    "wof:name":"Nakaugasele",
    "wof:placetype":"locality"
},
  "geometry": {"coordinates":[178.37861999999996,-18.95235],"type":"Point"}
}