{
  "type": "Feature",
  "properties": {
    "gn:admin1_code":"05",
    "gn:admin2_code":"2198946",
    "gn:asciiname":"Namuaimada",
    "gn:country_code":"FJ",
    "gn:dem":9,
    "gn:feature_class":"P",
    "gn:feature_code":"PPL",
    "gn:name":"Namuaimada",
    "gn:population":0,
    "gn:timezone":"Pacific/Fiji",
    "iso:country":"FJ",
    "name:fij_x_preferred":[
        "Namuaimada"
    ],
    "name:fij_x_variant":[
        "Namuaimanda"
    ],
    "wof:name":"Namuaimada",
    "wof:placetype":"locality"
},
  "geometry": {"coordinates":[178.25574,-17.40553],"type":"Point"}
}