{
  "type": "Feature",
  "properties": {
    "gn:admin1_code":"01",
    "gn:admin2_code":"2198131",
    "gn:asciiname":"Bau-Lomanikoro",
    "gn:country_code":"FJ",
    "gn:dem":10,
    "gn:feature_class":"P",
    "gn:feature_code":"PPL",
    "gn:name":"Bau-Lomanikoro",
    "gn:population":0,
    "gn:timezone":"Pacific/Fiji",
    "iso:country":"FJ",
    "name:fij_x_preferred":[
        "Bau-Lomanikoro"
    ],
    "wof:name":"Bau-Lomanikoro",
    "wof:placetype":"locality"
},
  "geometry": {"coordinates":[178.61383999999995,-17.9721],"type":"Point"}
}