{
  "type": "Feature",
  "properties": {
    "gn:admin1_code":"05",
    "gn:admin2_code":"2201984",
    "gn:asciiname":"Draubuta",
    "gn:country_code":"FJ",
    "gn:dem":164,
    "gn:feature_class":"P",
    "gn:feature_code":"PPL",
    "gn:name":"Draubuta",
    "gn:population":0,
    "gn:timezone":"Pacific/Fiji",
    "iso:country":"FJ",
    "name:fij_x_preferred":[
        "Draubuta"
    ],
    "name:und_x_variant":[
        "Ndrambuta",
        "Ndraumbuta"
    ],
    "wof:name":"Draubuta",
    "wof:placetype":"locality"
},
  "geometry": {"coordinates":[177.90031999999999,-17.92313],"type":"Point"}
}