{
  "type": "Feature",
  "properties": {
    "gn:admin1_code":"01",
    "gn:admin2_code":"2203150",
    "gn:asciiname":"Nacokaika",
    "gn:country_code":"FJ",
    "gn:dem":15,
    "gn:feature_class":"P",
    "gn:feature_code":"PPL",
    "gn:name":"Nacokaika",
    "gn:population":0,
    "gn:timezone":"Pacific/Fiji",
    "iso:country":"FJ",
    "name:fij_x_preferred":[
        "Nacokaika"
    ],
    "name:und_x_variant":[
        "Nathokeka",
        "Nathokaika"
    ],
    "wof:name":"Nacokaika",
    "wof:placetype":"locality"
},
  "geometry": {"coordinates":[178.42455000000001,-17.97056],"type":"Point"}
}