{
  "type": "Feature",
  "properties": {
    "gn:admin1_code":"01",
    "gn:admin2_code":"2198411",
    "gn:asciiname":"Beqa Settlement",
    "gn:country_code":"FJ",
    "gn:dem":48,
    "gn:feature_class":"P",
    "gn:feature_code":"PPL",
    "gn:name":"Beqa Settlement",
    "gn:population":0,
    "gn:timezone":"Pacific/Fiji",
    "iso:country":"FJ",
    "name:fij_x_preferred":[
        "Beqa Settlement"
    ],
    "name:und_x_variant":[
        "Bega",
        "Beka",
        "Mbengga"
    ],
    "wof:name":"Beqa Settlement",
    "wof:placetype":"locality"
},
  "geometry": {"coordinates":[178.05538000000001,-18.09412],"type":"Point"}
}