{
  "type": "Feature",
  "properties": {
    "gn:admin1_code":"5.0",
    "gn:admin2_code":"2201984.0",
    "gn:asciiname":"Tagaqe",
    "gn:country_code":"FJ",
    "gn:dem":10,
    "gn:feature_class":"P",
    "gn:feature_code":"PPL",
    "gn:name":"Tagaqe",
    "gn:population":0,
    "gn:timezone":"Pacific/Fiji",
    "iso:country":"FJ",
    "name:fij_x_preferred":[
        "Tagaqe"
    ],
    "name:und_x_variant":[
        "Tanganghi",
        "Tangangi",
        "Tangangge"
    ],
    "wof:name":"Tagaqe",
    "wof:placetype":"locality"
},
  "geometry": {"coordinates":[177.65754999999999,-18.19601],"type":"Point"}
}