{
  "type": "Feature",
  "properties": {
    "gn:admin1_code":"05",
    "gn:admin2_code":"2201984",
    "gn:asciiname":"Yaroso Settlement",
    "gn:country_code":"FJ",
    "gn:dem":79,
    "gn:feature_class":"P",
    "gn:feature_code":"PPL",
    "gn:name":"Yaroso Settlement",
    "gn:population":0,
    "gn:timezone":"Pacific/Fiji",
    "iso:country":"FJ",
    "name:fij_x_preferred":[
        "Yaroso Settlement"
    ],
    "wof:name":"Yaroso Settlement",
    "wof:placetype":"locality"
},
  "geometry": {"coordinates":[177.77603999999999,-17.91394],"type":"Point"}
}