{
  "type": "Feature",
  "properties": {
    "gn:admin1_code":"05",
    "gn:admin2_code":"2201984",
    "gn:asciiname":"Nadurumoli Settlement",
    "gn:country_code":"FJ",
    "gn:dem":38,
    "gn:feature_class":"P",
    "gn:feature_code":"PPL",
    "gn:name":"Nadurumoli Settlement",
    "gn:population":0,
    "gn:timezone":"Pacific/Fiji",
    "iso:country":"FJ",
    "name:fij_x_preferred":[
        "Nadurumoli Settlement"
    ],
    "wof:name":"Nadurumoli Settlement",
    "wof:placetype":"locality"
},
  "geometry": {"coordinates":[177.75722999999999,-17.88456],"type":"Point"}
}