{
  "type": "Feature",
  "properties": {
    "gn:admin1_code":"01",
    "gn:admin2_code":"2203150",
    "gn:asciiname":"Nairukuruku",
    "gn:country_code":"FJ",
    "gn:dem":40,
    "gn:feature_class":"P",
    "gn:feature_code":"PPL",
    "gn:name":"Nairukuruku",
    "gn:population":0,
    "gn:timezone":"Pacific/Fiji",
    "iso:country":"FJ",
    "name:fij_x_preferred":[
        "Nairukuruku"
    ],
    "wof:name":"Nairukuruku",
    "wof:placetype":"locality"
},
  "geometry": {"coordinates":[178.28468999999996,-17.81273],"type":"Point"}
}