{
  "type": "Feature",
  "properties": {
    "gn:admin1_code":"02",
    "gn:admin2_code":"2204318",
    "gn:asciiname":"Naqala Settlement",
    "gn:country_code":"FJ",
    "gn:dem":259,
    "gn:feature_class":"P",
    "gn:feature_code":"PPL",
    "gn:name":"Naqala Settlement",
    "gn:population":0,
    "gn:timezone":"Pacific/Fiji",
    "iso:country":"FJ",
    "name:fij_x_preferred":[
        "Naqala Settlement"
    ],
    "wof:name":"Naqala Settlement",
    "wof:placetype":"locality"
},
  "geometry": {"coordinates":[179.39580000000001,-17.27323],"type":"Point"}
}