{
  "type": "Feature",
  "properties": {
    "gn:admin1_code":"02",
    "gn:admin2_code":"8617786",
    "gn:asciiname":"Matavuralevu Settlement",
    "gn:country_code":"FJ",
    "gn:dem":39,
    "gn:feature_class":"P",
    "gn:feature_code":"PPL",
    "gn:name":"Matavuralevu Settlement",
    "gn:population":0,
    "gn:timezone":"Pacific/Fiji",
    "iso:country":"FJ",
    "name:fij_x_preferred":[
        "Matavuralevu Settlement"
    ],
    "wof:name":"Matavuralevu Settlement",
    "wof:placetype":"locality"
},
  "geometry": {"coordinates":[178.44748999999999,-19.01257],"type":"Point"}
}