{
  "type": "Feature",
  "properties": {
    "gn:admin1_code":"5.0",
    "gn:asciiname":"Savusavu",
    "gn:country_code":"FJ",
    "gn:dem":52,
    "gn:feature_class":"P",
    "gn:feature_code":"PPL",
    "gn:name":"Savusavu",
    "gn:population":0,
    "gn:timezone":"Pacific/Fiji",
    "iso:country":"FJ",
    "name:fij_x_preferred":[
        "Savusavu"
    ],
    "wof:name":"Savusavu",
    "wof:placetype":"locality"
},
  "geometry": {"coordinates":[178.25,-17.56667],"type":"Point"}
}