{
  "type": "Feature",
  "properties": {
    "gn:admin1_code":"5.0",
    "gn:asciiname":"Savusavu",
    "gn:country_code":"FJ",
    "gn:dem":52,
    "gn:feature_class":"P",
    "gn:feature_code":"PPL",
    "gn:name":"Savusavu",
    "gn:population":0,
    "gn:timezone":"Pacific/Fiji",
    "iso:country":"FJ",
    "name:ara_x_preferred":[
        "\u0633\u0627\u0641\u0648\u0633\u0627\u0641\u0648"
    ],
    "name:ceb_x_preferred":[
        "Savusavu"
    ],
    "name:deu_x_preferred":[
        "Savusavu"
    ],
    "name:fij_x_preferred":[
        "Savusavu"
    ],
    "name:fin_x_preferred":[
        "Savusavu"
    ],
    "name:fra_x_preferred":[
        "Savusavu"
    ],
    "name:hif_x_preferred":[
        "Savusavu"
    ],
    "name:hin_x_preferred":[
        "\u0938\u093e\u0935\u0942\u0938\u093e\u0935\u0942"
    ],
    "name:jpn_x_preferred":[
        "\u30b5\u30d6\u30b5\u30d6"
    ],
    "name:kor_x_preferred":[
        "\uc0ac\ubd80\uc0ac\ubd80"
    ],
    "name:lit_x_preferred":[
        "Savusavu"
    ],
    "name:nld_x_preferred":[
        "Savusavu"
    ],
    "name:pol_x_preferred":[
        "Savusavu"
    ],
    "name:rus_x_preferred":[
        "\u0421\u0430\u0432\u0443\u0441\u0430\u0432\u0443"
    ],
    "name:swe_x_preferred":[
        "Savusavu"
    ],
    "name:tam_x_preferred":[
        "\u0b9a\u0bb5\u0bc1\u0b9a\u0bb5\u0bc1"
    ],
    "name:zho_x_preferred":[
        "\u8428\u6b66\u8428\u6b66"
    ],
    "wof:name":"Savusavu",
    "wof:placetype":"locality"
},
  "geometry": {"coordinates":[178.25,-17.56667],"type":"Point"}
}