{
  "type": "Feature",
  "properties": {
    "gn:admin1_code":"01",
    "gn:admin2_code":"2198131",
    "gn:asciiname":"Naburenivalu",
    "gn:country_code":"FJ",
    "gn:dem":22,
    "gn:feature_class":"P",
    "gn:feature_code":"PPL",
    "gn:name":"Naburenivalu",
    "gn:population":0,
    "gn:timezone":"Pacific/Fiji",
    "iso:country":"FJ",
    "name:fij_x_preferred":[
        "Naburenivalu"
    ],
    "name:fij_x_variant":[
        "Mburenivalu"
    ],
    "wof:name":"Naburenivalu",
    "wof:placetype":"locality"
},
  "geometry": {"coordinates":[178.56358,-17.70424],"type":"Point"}
}