{
  "type": "Feature",
  "properties": {
    "gn:admin1_code":"00",
    "gn:asciiname":"Keteira",
    "gn:cc2":"FJ",
    "gn:country_code":"FJ",
    "gn:dem":1,
    "gn:feature_class":"P",
    "gn:feature_code":"PPL",
    "gn:name":"Keteira",
    "gn:population":0,
    "gn:timezone":"Pacific/Fiji",
    "iso:country":"FJ",
    "name:und_x_variant":[
        "Kiti-i-ra",
        "Keteira"
    ],
    "wof:name":"Keteira",
    "wof:placetype":"locality"
},
  "geometry": {"coordinates":[179.90000000000001,-18.61667000000001],"type":"Point"}
}