{
  "type": "Feature",
  "properties": {
    "gn:admin1_code":"03",
    "gn:admin2_code":"2197820",
    "gn:asciiname":"Caumudremudre Settlement",
    "gn:country_code":"FJ",
    "gn:dem":21,
    "gn:feature_class":"P",
    "gn:feature_code":"PPL",
    "gn:name":"Caumudremudre Settlement",
    "gn:population":0,
    "gn:timezone":"Pacific/Fiji",
    "iso:country":"FJ",
    "name:fij_x_preferred":[
        "Caumudremudre Settlement"
    ],
    "wof:name":"Caumudremudre Settlement",
    "wof:placetype":"locality"
},
  "geometry": {"coordinates":[179.99271000000005,-16.80508],"type":"Point"}
}