{
  "type": "Feature",
  "properties": {
    "gn:admin1_code":"03",
    "gn:admin2_code":"2203875",
    "gn:asciiname":"Nambukandongo",
    "gn:country_code":"FJ",
    "gn:dem":7,
    "gn:feature_class":"P",
    "gn:feature_code":"PPL",
    "gn:name":"Nambukandongo",
    "gn:population":0,
    "gn:timezone":"Pacific/Fiji",
    "iso:country":"FJ",
    "name:fij_x_preferred":[
        "Nambukandongo"
    ],
    "name:fij_x_variant":[
        "Nabukadogo"
    ],
    "wof:name":"Nambukandongo",
    "wof:placetype":"locality"
},
  "geometry": {"coordinates":[179.11118000000005,-16.44466],"type":"Point"}
}