{
  "type": "Feature",
  "properties": {
    "gn:admin1_code":"01",
    "gn:admin2_code":"2203150",
    "gn:asciiname":"Makoi",
    "gn:country_code":"FJ",
    "gn:dem":50,
    "gn:feature_class":"P",
    "gn:feature_code":"PPL",
    "gn:name":"Makoi",
    "gn:population":0,
    "gn:timezone":"Pacific/Fiji",
    "iso:country":"FJ",
    "name:fij_x_preferred":[
        "Makoi"
    ],
    "wof:name":"Makoi",
    "wof:placetype":"locality"
},
  "geometry": {"coordinates":[178.49849,-18.07256],"type":"Point"}
}