{
  "type": "Feature",
  "properties": {
    "gn:admin1_code":"01",
    "gn:admin2_code":"2198876",
    "gn:asciiname":"Nukutubu",
    "gn:country_code":"FJ",
    "gn:dem":4,
    "gn:feature_class":"P",
    "gn:feature_code":"PPL",
    "gn:name":"Nukutubu",
    "gn:population":0,
    "gn:timezone":"Pacific/Fiji",
    "iso:country":"FJ",
    "name:fij_x_preferred":[
        "Nukutubu"
    ],
    "name:fij_x_variant":[
        "Nukutumbu"
    ],
    "wof:name":"Nukutubu",
    "wof:placetype":"locality"
},
  "geometry": {"coordinates":[178.55701000000005,-18.10038],"type":"Point"}
}