{
  "type": "Feature",
  "properties": {
    "gn:admin1_code":"05",
    "gn:admin2_code":"2201984",
    "gn:asciiname":"Rakirakilevu Settlement",
    "gn:country_code":"FJ",
    "gn:dem":42,
    "gn:feature_class":"P",
    "gn:feature_code":"PPL",
    "gn:name":"Rakirakilevu Settlement",
    "gn:population":0,
    "gn:timezone":"Pacific/Fiji",
    "iso:country":"FJ",
    "name:fij_x_preferred":[
        "Rakirakilevu Settlement"
    ],
    "wof:name":"Rakirakilevu Settlement",
    "wof:placetype":"locality"
},
  "geometry": {"coordinates":[177.4907,-18.14215],"type":"Point"}
}