{
  "type": "Feature",
  "properties": {
    "gn:admin1_code":"03",
    "gn:admin2_code":"2203651",
    "gn:asciiname":"Nabuni Settlement",
    "gn:country_code":"FJ",
    "gn:dem":12,
    "gn:feature_class":"P",
    "gn:feature_code":"PPL",
    "gn:name":"Nabuni Settlement",
    "gn:population":0,
    "gn:timezone":"Pacific/Fiji",
    "iso:country":"FJ",
    "name:fij_x_preferred":[
        "Nabuni Settlement"
    ],
    "wof:name":"Nabuni Settlement",
    "wof:placetype":"locality"
},
  "geometry": {"coordinates":[178.86588999999995,-16.85459],"type":"Point"}
}