{
  "type": "Feature",
  "properties": {
    "gn:admin1_code":"05",
    "gn:admin2_code":"2198946",
    "gn:asciiname":"Taina Settlement",
    "gn:country_code":"FJ",
    "gn:dem":32,
    "gn:feature_class":"P",
    "gn:feature_code":"PPL",
    "gn:name":"Taina Settlement",
    "gn:population":0,
    "gn:timezone":"Pacific/Fiji",
    "iso:country":"FJ",
    "name:fij_x_preferred":[
        "Taina Settlement"
    ],
    "wof:name":"Taina Settlement",
    "wof:placetype":"locality"
},
  "geometry": {"coordinates":[178.20830000000001,-17.49572],"type":"Point"}
}