{
  "type": "Feature",
  "properties": {
    "gn:admin1_code":"01",
    "gn:admin2_code":"2198411",
    "gn:asciiname":"Nakorovou",
    "gn:country_code":"FJ",
    "gn:dem":14,
    "gn:feature_class":"P",
    "gn:feature_code":"PPL",
    "gn:name":"Nakorovou",
    "gn:population":0,
    "gn:timezone":"Pacific/Fiji",
    "iso:country":"FJ",
    "name:fij_x_preferred":[
        "Nakorovou"
    ],
    "name:und_x_variant":[
        "Kovo Vu",
        "Korovou"
    ],
    "wof:name":"Nakorovou",
    "wof:placetype":"locality"
},
  "geometry": {"coordinates":[177.97251,-18.2423],"type":"Point"}
}