{
  "type": "Feature",
  "properties": {
    "gn:admin1_code":"01",
    "gn:admin2_code":"2198131",
    "gn:asciiname":"Logani",
    "gn:country_code":"FJ",
    "gn:dem":84,
    "gn:feature_class":"P",
    "gn:feature_code":"PPL",
    "gn:name":"Logani",
    "gn:population":0,
    "gn:timezone":"Pacific/Fiji",
    "iso:country":"FJ",
    "name:fij_x_preferred":[
        "Logani"
    ],
    "name:und_x_variant":[
        "Lungani",
        "Longani"
    ],
    "wof:name":"Logani",
    "wof:placetype":"locality"
},
  "geometry": {"coordinates":[178.54830999999999,-17.95331000000001],"type":"Point"}
}