{
  "type": "Feature",
  "properties": {
    "gn:admin1_code":"1.0",
    "gn:asciiname":"Waivunu",
    "gn:cc2":"FJ",
    "gn:country_code":"FJ",
    "gn:dem":105,
    "gn:feature_class":"P",
    "gn:feature_code":"PPL",
    "gn:name":"Waivunu",
    "gn:population":0,
    "gn:timezone":"Pacific/Fiji",
    "iso:country":"FJ",
    "name:und_x_variant":[
        "Vaivunu",
        "Waivunu"
    ],
    "wof:name":"Waivunu",
    "wof:placetype":"locality"
},
  "geometry": {"coordinates":[177.98333,-18.25],"type":"Point"}
}