{
  "type": "Feature",
  "properties": {
    "gn:admin1_code":"00",
    "gn:asciiname":"Natuvatuvavatu",
    "gn:country_code":"FJ",
    "gn:dem":49,
    "gn:feature_class":"P",
    "gn:feature_code":"PPL",
    "gn:name":"Natuvatuvavatu",
    "gn:population":0,
    "gn:timezone":"Pacific/Fiji",
    "iso:country":"FJ",
    "name:fij_x_preferred":[
        "Natuvatuvavatu"
    ],
    "wof:name":"Natuvatuvavatu",
    "wof:placetype":"locality"
},
  "geometry": {"coordinates":[178.38933,-17.67406],"type":"Point"}
}