{
  "type": "Feature",
  "properties": {
    "gn:admin1_code":"05",
    "gn:admin2_code":"2203798",
    "gn:asciiname":"Koro",
    "gn:country_code":"FJ",
    "gn:dem":181,
    "gn:feature_class":"P",
    "gn:feature_code":"PPL",
    "gn:name":"Koro",
    "gn:population":0,
    "gn:timezone":"Pacific/Fiji",
    "iso:country":"FJ",
    "name:ceb_x_preferred":[
        "Koro"
    ],
    "name:ces_x_preferred":[
        "Koro"
    ],
    "name:deu_x_preferred":[
        "Koro"
    ],
    "name:epo_x_preferred":[
        "Koro"
    ],
    "name:eus_x_preferred":[
        "Koro"
    ],
    "name:fij_x_preferred":[
        "Koro"
    ],
    "name:fin_x_preferred":[
        "Koro"
    ],
    "name:fra_x_preferred":[
        "Koro"
    ],
    "name:hrv_x_preferred":[
        "Koro"
    ],
    "name:ido_x_preferred":[
        "Koro"
    ],
    "name:ita_x_preferred":[
        "Koro"
    ],
    "name:lit_x_preferred":[
        "Koras"
    ],
    "name:lmo_x_preferred":[
        "Koro"
    ],
    "name:nld_x_preferred":[
        "Koro"
    ],
    "name:spa_x_preferred":[
        "Koro"
    ],
    "name:swa_x_preferred":[
        "Koro"
    ],
    "name:swe_x_preferred":[
        "Koro"
    ],
    "name:tur_x_preferred":[
        "Koro"
    ],
    "wof:name":"Koro",
    "wof:placetype":"locality"
},
  "geometry": {"coordinates":[177.90718000000001,-17.70857999999999],"type":"Point"}
}