{
  "type": "Feature",
  "properties": {
    "gn:admin1_code":"05",
    "gn:admin2_code":"2198946",
    "gn:asciiname":"Nakorovou",
    "gn:country_code":"FJ",
    "gn:dem":19,
    "gn:feature_class":"P",
    "gn:feature_code":"PPL",
    "gn:name":"Nakorovou",
    "gn:population":0,
    "gn:timezone":"Pacific/Fiji",
    "iso:country":"FJ",
    "name:fij_x_preferred":[
        "Nakorovou"
    ],
    "name:fij_x_variant":[
        "Korovou"
    ],
    "wof:name":"Nakorovou",
    "wof:placetype":"locality"
},
  "geometry": {"coordinates":[178.28389999999999,-17.49715],"type":"Point"}
}