{
  "type": "Feature",
  "properties": {
    "gn:admin1_code":"5.0",
    "gn:admin2_code":"2203798.0",
    "gn:asciiname":"Tamasua",
    "gn:country_code":"FJ",
    "gn:dem":5,
    "gn:feature_class":"P",
    "gn:feature_code":"PPL",
    "gn:name":"Tamasua",
    "gn:population":0,
    "gn:timezone":"Pacific/Fiji",
    "iso:country":"FJ",
    "name:fij_x_preferred":[
        "Tamasua"
    ],
    "name:fij_x_variant":[
        "Tamusua"
    ],
    "wof:name":"Tamasua",
    "wof:placetype":"locality"
},
  "geometry": {"coordinates":[177.44887,-16.84108],"type":"Point"}
}