{
  "type": "Feature",
  "properties": {
    "gn:admin1_code":"03",
    "gn:admin2_code":"2197820",
    "gn:asciiname":"Korokacivi Settlement",
    "gn:country_code":"FJ",
    "gn:dem":41,
    "gn:feature_class":"P",
    "gn:feature_code":"PPL",
    "gn:name":"Korokacivi Settlement",
    "gn:population":0,
    "gn:timezone":"Pacific/Fiji",
    "iso:country":"FJ",
    "name:fij_x_preferred":[
        "Korokacivi Settlement"
    ],
    "wof:name":"Korokacivi Settlement",
    "wof:placetype":"locality"
},
  "geometry": {"coordinates":[179.11282,-16.74367],"type":"Point"}
}