{
  "type": "Feature",
  "properties": {
    "gn:admin1_code":"02",
    "gn:admin2_code":"8617786",
    "gn:asciiname":"Matanuku",
    "gn:country_code":"FJ",
    "gn:dem":14,
    "gn:feature_class":"P",
    "gn:feature_code":"PPL",
    "gn:name":"Matanuku",
    "gn:population":0,
    "gn:timezone":"Pacific/Fiji",
    "iso:country":"FJ",
    "name:fij_x_preferred":[
        "Matanuku"
    ],
    "wof:name":"Matanuku",
    "wof:placetype":"locality"
},
  "geometry": {"coordinates":[178.10086000000001,-19.16555],"type":"Point"}
}