{
  "type": "Feature",
  "properties": {
    "gn:admin1_code":"01",
    "gn:admin2_code":"2198876",
    "gn:asciiname":"Narocivo",
    "gn:country_code":"FJ",
    "gn:dem":9,
    "gn:feature_class":"P",
    "gn:feature_code":"PPL",
    "gn:name":"Narocivo",
    "gn:population":0,
    "gn:timezone":"Pacific/Fiji",
    "iso:country":"FJ",
    "name:fij_x_preferred":[
        "Narocivo"
    ],
    "name:fij_x_variant":[
        "Narothivo"
    ],
    "wof:name":"Narocivo",
    "wof:placetype":"locality"
},
  "geometry": {"coordinates":[178.54277999999999,-18.12757],"type":"Point"}
}