{
  "type": "Feature",
  "properties": {
    "gn:admin1_code":"03",
    "gn:admin2_code":"2203651",
    "gn:asciiname":"Namulomulo Settlement",
    "gn:country_code":"FJ",
    "gn:dem":9,
    "gn:feature_class":"P",
    "gn:feature_code":"PPL",
    "gn:name":"Namulomulo Settlement",
    "gn:population":0,
    "gn:timezone":"Pacific/Fiji",
    "iso:country":"FJ",
    "name:fij_x_preferred":[
        "Namulomulo Settlement"
    ],
    "wof:name":"Namulomulo Settlement",
    "wof:placetype":"locality"
},
  "geometry": {"coordinates":[178.68826999999999,-16.98371],"type":"Point"}
}