{
  "type": "Feature",
  "properties": {
    "gn:admin1_code":"05",
    "gn:admin2_code":"2201984",
    "gn:asciiname":"Koronisagana",
    "gn:country_code":"FJ",
    "gn:dem":36,
    "gn:feature_class":"P",
    "gn:feature_code":"PPL",
    "gn:name":"Koronisagana",
    "gn:population":0,
    "gn:timezone":"Pacific/Fiji",
    "iso:country":"FJ",
    "name:fij_x_preferred":[
        "Koronisagana"
    ],
    "name:und_x_variant":[
        "Koronisangana"
    ],
    "wof:name":"Koronisagana",
    "wof:placetype":"locality"
},
  "geometry": {"coordinates":[177.62790000000001,-17.97247999999999],"type":"Point"}
}