{
  "type": "Feature",
  "properties": {
    "gn:admin1_code":"03",
    "gn:admin2_code":"2197820",
    "gn:asciiname":"Lamini",
    "gn:country_code":"FJ",
    "gn:dem":11,
    "gn:feature_class":"P",
    "gn:feature_code":"PPL",
    "gn:name":"Lamini",
    "gn:population":0,
    "gn:timezone":"Pacific/Fiji",
    "iso:country":"FJ",
    "name:ara_x_preferred":[
        "\u0644\u0627\u0645\u0627\u0648\u064a\u0629"
    ],
    "name:fij_x_preferred":[
        "Lamini"
    ],
    "name:fry_x_preferred":[
        "Lama-eftigen"
    ],
    "name:hun_x_preferred":[
        "Lamini"
    ],
    "name:kor_x_preferred":[
        "\ub77c\ub9c8\uc871"
    ],
    "name:lav_x_preferred":[
        "Lamu cilts"
    ],
    "name:nno_x_preferred":[
        "Lamadyr"
    ],
    "name:nor_x_preferred":[
        "Lamadyr"
    ],
    "name:spa_x_preferred":[
        "Lamini"
    ],
    "name:zho_x_preferred":[
        "\u7f8e\u6d32\u9a7c"
    ],
    "wof:name":"Lamini",
    "wof:placetype":"locality"
},
  "geometry": {"coordinates":[-179.96501999999995,-16.76512],"type":"Point"}
}