{
  "type": "Feature",
  "properties": {
    "gn:admin1_code":"03",
    "gn:admin2_code":"2197820",
    "gn:asciiname":"Lamini",
    "gn:country_code":"FJ",
    "gn:dem":11,
    "gn:feature_class":"P",
    "gn:feature_code":"PPL",
    "gn:name":"Lamini",
    "gn:population":0,
    "gn:timezone":"Pacific/Fiji",
    "iso:country":"FJ",
    "name:fij_x_preferred":[
        "Lamini"
    ],
    "wof:name":"Lamini",
    "wof:placetype":"locality"
},
  "geometry": {"coordinates":[-179.96501999999995,-16.76512],"type":"Point"}
}