{
  "type": "Feature",
  "properties": {
    "gn:admin1_code":"3.0",
    "gn:asciiname":"Vatolotolo",
    "gn:country_code":"FJ",
    "gn:dem":-9999,
    "gn:feature_class":"P",
    "gn:feature_code":"PPL",
    "gn:name":"Vatolotolo",
    "gn:population":0,
    "gn:timezone":"Pacific/Fiji",
    "iso:country":"FJ",
    "name:fij_x_preferred":[
        "Vatolotolo"
    ],
    "wof:name":"Vatolotolo",
    "wof:placetype":"locality"
},
  "geometry": {"coordinates":[179.90000000000001,-16.75],"type":"Point"}
}