{
  "type": "Feature",
  "properties": {
    "gn:admin1_code":"5.0",
    "gn:admin2_code":"2201984.0",
    "gn:asciiname":"Yako",
    "gn:country_code":"FJ",
    "gn:dem":6,
    "gn:feature_class":"P",
    "gn:feature_code":"PPL",
    "gn:name":"Yako",
    "gn:population":0,
    "gn:timezone":"Pacific/Fiji",
    "iso:country":"FJ",
    "name:ceb_x_preferred":[
        "Yako"
    ],
    "name:fij_x_preferred":[
        "Yako"
    ],
    "name:swe_x_preferred":[
        "Yako"
    ],
    "wof:name":"Yako",
    "wof:placetype":"locality"
},
  "geometry": {"coordinates":[177.33518000000001,-17.86245],"type":"Point"}
}