{
  "type": "Feature",
  "properties": {
    "gn:admin1_code":"5.0",
    "gn:admin2_code":"2201984.0",
    "gn:asciiname":"Yako",
    "gn:country_code":"FJ",
    "gn:dem":6,
    "gn:feature_class":"P",
    "gn:feature_code":"PPL",
    "gn:name":"Yako",
    "gn:population":0,
    "gn:timezone":"Pacific/Fiji",
    "iso:country":"FJ",
    "name:ara_x_preferred":[
        "\u064a\u0627\u0643\u0648"
    ],
    "name:ben_x_preferred":[
        "\u0987\u09df\u09be\u0995\u09cb"
    ],
    "name:ceb_x_preferred":[
        "Yako"
    ],
    "name:ell_x_preferred":[
        "\u0393\u03b9\u03ac\u03ba\u03bf"
    ],
    "name:fas_x_preferred":[
        "\u06cc\u0627\u06a9\u0648"
    ],
    "name:fij_x_preferred":[
        "Yako"
    ],
    "name:hin_x_preferred":[
        "\u092f\u093e\u0915\u094b"
    ],
    "name:hun_x_preferred":[
        "Yako"
    ],
    "name:ind_x_preferred":[
        "Yako"
    ],
    "name:kor_x_preferred":[
        "\uc57c\ucf54"
    ],
    "name:swe_x_preferred":[
        "Yako"
    ],
    "name:tur_x_preferred":[
        "Yako"
    ],
    "name:vie_x_preferred":[
        "Yako"
    ],
    "wof:name":"Yako",
    "wof:placetype":"locality"
},
  "geometry": {"coordinates":[177.33518000000001,-17.86245],"type":"Point"}
}