{
  "type": "Feature",
  "properties": {
    "gn:admin1_code":"05",
    "gn:admin2_code":"2201984",
    "gn:asciiname":"Waivaruru Settlement",
    "gn:country_code":"FJ",
    "gn:dem":549,
    "gn:feature_class":"P",
    "gn:feature_code":"PPL",
    "gn:name":"Waivaruru Settlement",
    "gn:population":0,
    "gn:timezone":"Pacific/Fiji",
    "iso:country":"FJ",
    "name:fij_x_preferred":[
        "Waivaruru Settlement"
    ],
    "wof:name":"Waivaruru Settlement",
    "wof:placetype":"locality"
},
  "geometry": {"coordinates":[177.83526000000001,-17.79742000000001],"type":"Point"}
}