{
  "type": "Feature",
  "properties": {
    "gn:admin1_code":"03",
    "gn:admin2_code":"2197820",
    "gn:asciiname":"Vunidilo Settlement",
    "gn:country_code":"FJ",
    "gn:dem":157,
    "gn:feature_class":"P",
    "gn:feature_code":"PPL",
    "gn:name":"Vunidilo Settlement",
    "gn:population":0,
    "gn:timezone":"Pacific/Fiji",
    "iso:country":"FJ",
    "name:fij_x_preferred":[
        "Vunidilo Settlement"
    ],
    "wof:name":"Vunidilo Settlement",
    "wof:placetype":"locality"
},
  "geometry": {"coordinates":[179.92146,-16.98598],"type":"Point"}
}