{
  "type": "Feature",
  "properties": {
    "gn:admin1_code":"05",
    "gn:admin2_code":"2203798",
    "gn:asciiname":"Sonadradra Settlement",
    "gn:country_code":"FJ",
    "gn:dem":506,
    "gn:feature_class":"P",
    "gn:feature_code":"PPL",
    "gn:name":"Sonadradra Settlement",
    "gn:population":0,
    "gn:timezone":"Pacific/Fiji",
    "iso:country":"FJ",
    "name:fij_x_preferred":[
        "Sonadradra Settlement"
    ],
    "wof:name":"Sonadradra Settlement",
    "wof:placetype":"locality"
},
  "geometry": {"coordinates":[177.72118,-17.74679],"type":"Point"}
}