{
  "type": "Feature",
  "properties": {
    "gn:admin1_code":"1.0",
    "gn:admin2_code":"2198131.0",
    "gn:asciiname":"Cautata",
    "gn:country_code":"FJ",
    "gn:dem":7,
    "gn:feature_class":"P",
    "gn:feature_code":"PPL",
    "gn:name":"Cautata",
    "gn:population":0,
    "gn:timezone":"Pacific/Fiji",
    "iso:country":"FJ",
    "name:fij_x_preferred":[
        "Cautata"
    ],
    "name:fij_x_variant":[
        "Thautata"
    ],
    "wof:name":"Cautata",
    "wof:placetype":"locality"
},
  "geometry": {"coordinates":[178.62336000000005,-17.99617000000001],"type":"Point"}
}