{
  "type": "Feature",
  "properties": {
    "gn:admin1_code":"01",
    "gn:asciiname":"Matathula",
    "gn:country_code":"FJ",
    "gn:dem":-9999,
    "gn:feature_class":"P",
    "gn:feature_code":"PPL",
    "gn:name":"Matathula",
    "gn:population":0,
    "gn:timezone":"Pacific/Fiji",
    "iso:country":"FJ",
    "name:fij_x_preferred":[
        "Matathula"
    ],
    "wof:name":"Matathula",
    "wof:placetype":"locality"
},
  "geometry": {"coordinates":[178.56666999999999,-17.76667],"type":"Point"}
}