{
  "type": "Feature",
  "properties": {
    "gn:admin1_code":"2.0",
    "gn:admin2_code":"8617786.0",
    "gn:asciiname":"Vunisei",
    "gn:country_code":"FJ",
    "gn:dem":9,
    "gn:feature_class":"P",
    "gn:feature_code":"PPL",
    "gn:name":"Vunisei",
    "gn:population":0,
    "gn:timezone":"Pacific/Fiji",
    "iso:country":"FJ",
    "name:fij_x_preferred":[
        "Vunisei"
    ],
    "wof:name":"Vunisei",
    "wof:placetype":"locality"
},
  "geometry": {"coordinates":[178.27526,-18.98116],"type":"Point"}
}