{
  "type": "Feature",
  "properties": {
    "gn:admin1_code":"01",
    "gn:admin2_code":"2198131",
    "gn:asciiname":"Wainivilimi Settlement",
    "gn:country_code":"FJ",
    "gn:dem":50,
    "gn:feature_class":"P",
    "gn:feature_code":"PPL",
    "gn:name":"Wainivilimi Settlement",
    "gn:population":0,
    "gn:timezone":"Pacific/Fiji",
    "iso:country":"FJ",
    "name:fij_x_preferred":[
        "Wainivilimi Settlement"
    ],
    "wof:name":"Wainivilimi Settlement",
    "wof:placetype":"locality"
},
  "geometry": {"coordinates":[178.48559,-17.73045],"type":"Point"}
}