{
  "type": "Feature",
  "properties": {
    "gn:admin1_code":"03",
    "gn:admin2_code":"2197820",
    "gn:asciiname":"Salialevu Settlement",
    "gn:country_code":"FJ",
    "gn:dem":20,
    "gn:feature_class":"P",
    "gn:feature_code":"PPL",
    "gn:name":"Salialevu Settlement",
    "gn:population":0,
    "gn:timezone":"Pacific/Fiji",
    "iso:country":"FJ",
    "name:fij_x_preferred":[
        "Salialevu Settlement"
    ],
    "name:fij_x_variant":[
        "Salialevu"
    ],
    "wof:name":"Salialevu Settlement",
    "wof:placetype":"locality"
},
  "geometry": {"coordinates":[179.99369999999999,-16.96838],"type":"Point"}
}