{
  "type": "Feature",
  "properties": {
    "gn:admin1_code":"02",
    "gn:admin2_code":"8617786",
    "gn:asciiname":"Nauciwai",
    "gn:country_code":"FJ",
    "gn:dem":21,
    "gn:feature_class":"P",
    "gn:feature_code":"PPL",
    "gn:name":"Nauciwai",
    "gn:population":0,
    "gn:timezone":"Pacific/Fiji",
    "iso:country":"FJ",
    "name:fij_x_preferred":[
        "Nauciwai"
    ],
    "name:fij_x_variant":[
        "Nauthiwai"
    ],
    "wof:name":"Nauciwai",
    "wof:placetype":"locality"
},
  "geometry": {"coordinates":[178.30668,-18.9527],"type":"Point"}
}