{
  "type": "Feature",
  "properties": {
    "gn:admin1_code":"03",
    "gn:admin2_code":"2203651",
    "gn:asciiname":"Vatubogi Settlement",
    "gn:country_code":"FJ",
    "gn:dem":30,
    "gn:feature_class":"P",
    "gn:feature_code":"PPL",
    "gn:name":"Vatubogi Settlement",
    "gn:population":0,
    "gn:timezone":"Pacific/Fiji",
    "iso:country":"FJ",
    "name:fij_x_preferred":[
        "Vatubogi Settlement"
    ],
    "wof:name":"Vatubogi Settlement",
    "wof:placetype":"locality"
},
  "geometry": {"coordinates":[178.56006000000005,-16.78868],"type":"Point"}
}