{
  "type": "Feature",
  "properties": {
    "gn:admin1_code":"01",
    "gn:admin2_code":"2203150",
    "gn:asciiname":"Laqere",
    "gn:country_code":"FJ",
    "gn:dem":24,
    "gn:feature_class":"P",
    "gn:feature_code":"PPL",
    "gn:name":"Laqere",
    "gn:population":0,
    "gn:timezone":"Pacific/Fiji",
    "iso:country":"FJ",
    "name:fij_x_preferred":[
        "Laqere"
    ],
    "name:fij_x_variant":[
        "Langgere"
    ],
    "wof:name":"Laqere",
    "wof:placetype":"locality"
},
  "geometry": {"coordinates":[178.49861999999999,-18.08366],"type":"Point"}
}