{
  "type": "Feature",
  "properties": {
    "gn:admin1_code":"02",
    "gn:admin2_code":"8617786",
    "gn:asciiname":"Bulia",
    "gn:country_code":"FJ",
    "gn:dem":9,
    "gn:feature_class":"P",
    "gn:feature_code":"PPL",
    "gn:name":"Bulia",
    "gn:population":0,
    "gn:timezone":"Pacific/Fiji",
    "iso:country":"FJ",
    "name:ceb_x_preferred":[
        "Bulia"
    ],
    "name:fij_x_preferred":[
        "Bulia"
    ],
    "name:por_x_preferred":[
        "Bulia"
    ],
    "name:spa_x_preferred":[
        "Bulia"
    ],
    "name:swe_x_preferred":[
        "Bulia"
    ],
    "name:und_x_variant":[
        "Mbulia",
        "Mbuliya"
    ],
    "name:vie_x_preferred":[
        "Bulia"
    ],
    "name:war_x_preferred":[
        "Bulia"
    ],
    "wof:name":"Bulia",
    "wof:placetype":"locality"
},
  "geometry": {"coordinates":[178.53083000000001,-18.84373],"type":"Point"}
}