{
  "type": "Feature",
  "properties": {
    "gn:admin1_code":"05",
    "gn:admin2_code":"2201984",
    "gn:asciiname":"Nawamagi",
    "gn:country_code":"FJ",
    "gn:dem":17,
    "gn:feature_class":"P",
    "gn:feature_code":"PPL",
    "gn:name":"Nawamagi",
    "gn:population":0,
    "gn:timezone":"Pacific/Fiji",
    "iso:country":"FJ",
    "name:fij_x_preferred":[
        "Nawamagi"
    ],
    "name:und_x_variant":[
        "Nawamangimangi",
        "Nawamangi"
    ],
    "wof:name":"Nawamagi",
    "wof:placetype":"locality"
},
  "geometry": {"coordinates":[177.5446,-18.0969],"type":"Point"}
}