{
  "type": "Feature",
  "properties": {
    "gn:admin1_code":"05",
    "gn:admin2_code":"2203798",
    "gn:asciiname":"Balevuto",
    "gn:country_code":"FJ",
    "gn:dem":39,
    "gn:feature_class":"P",
    "gn:feature_code":"PPL",
    "gn:name":"Balevuto",
    "gn:population":0,
    "gn:timezone":"Pacific/Fiji",
    "iso:country":"FJ",
    "name:fij_x_preferred":[
        "Balevuto"
    ],
    "name:und_x_variant":[
        "Mbalevuto"
    ],
    "wof:name":"Balevuto",
    "wof:placetype":"locality"
},
  "geometry": {"coordinates":[177.72172,-17.64781],"type":"Point"}
}