{
  "type": "Feature",
  "properties": {
    "gn:admin1_code":"03",
    "gn:admin2_code":"2203651",
    "gn:asciiname":"Batiri Settlement",
    "gn:country_code":"FJ",
    "gn:dem":22,
    "gn:feature_class":"P",
    "gn:feature_code":"PPL",
    "gn:name":"Batiri Settlement",
    "gn:population":0,
    "gn:timezone":"Pacific/Fiji",
    "iso:country":"FJ",
    "name:fij_x_preferred":[
        "Batiri Settlement"
    ],
    "wof:name":"Batiri Settlement",
    "wof:placetype":"locality"
},
  "geometry": {"coordinates":[178.76039,-16.94763],"type":"Point"}
}