{
  "type": "Feature",
  "properties": {
    "gn:admin1_code":"04",
    "gn:asciiname":"Gaol",
    "gn:country_code":"FJ",
    "gn:dem":25,
    "gn:feature_class":"P",
    "gn:feature_code":"PPL",
    "gn:name":"Gaol",
    "gn:population":0,
    "gn:timezone":"Pacific/Fiji",
    "iso:country":"FJ",
    "name:fij_x_preferred":[
        "Gaol"
    ],
    "wof:name":"Gaol",
    "wof:placetype":"locality"
},
  "geometry": {"coordinates":[177.04709,-12.50172],"type":"Point"}
}