{
  "type": "Feature",
  "properties": {
    "gn:admin1_code":"01",
    "gn:admin2_code":"2198131",
    "gn:asciiname":"Luveidibuna Creek",
    "gn:country_code":"FJ",
    "gn:dem":25,
    "gn:feature_class":"P",
    "gn:feature_code":"PPL",
    "gn:name":"Luveidibuna Creek",
    "gn:population":0,
    "gn:timezone":"Pacific/Fiji",
    "iso:country":"FJ",
    "name:fij_x_preferred":[
        "Luveidibuna Creek"
    ],
    "wof:name":"Luveidibuna Creek",
    "wof:placetype":"locality"
},
  "geometry": {"coordinates":[178.46018999999995,-17.79107],"type":"Point"}
}