{
  "type": "Feature",
  "properties": {
    "gn:admin1_code":"01",
    "gn:admin2_code":"2198131",
    "gn:asciiname":"Naileqavatu Settlement",
    "gn:country_code":"FJ",
    "gn:dem":36,
    "gn:feature_class":"P",
    "gn:feature_code":"PPL",
    "gn:name":"Naileqavatu Settlement",
    "gn:population":0,
    "gn:timezone":"Pacific/Fiji",
    "iso:country":"FJ",
    "name:fij_x_preferred":[
        "Naileqavatu Settlement"
    ],
    "wof:name":"Naileqavatu Settlement",
    "wof:placetype":"locality"
},
  "geometry": {"coordinates":[178.37913999999995,-17.69706],"type":"Point"}
}