{
  "type": "Feature",
  "properties": {
    "gn:admin1_code":"00",
    "gn:asciiname":"Waiwai Settlement",
    "gn:country_code":"FJ",
    "gn:dem":520,
    "gn:feature_class":"P",
    "gn:feature_code":"PPL",
    "gn:name":"Waiwai Settlement",
    "gn:population":0,
    "gn:timezone":"Pacific/Fiji",
    "iso:country":"FJ",
    "name:fij_x_preferred":[
        "Waiwai Settlement"
    ],
    "wof:name":"Waiwai Settlement",
    "wof:placetype":"locality"
},
  "geometry": {"coordinates":[177.58283,-17.81875],"type":"Point"}
}