{
  "type": "Feature",
  "properties": {
    "gn:admin1_code":"01",
    "gn:admin2_code":"2203150",
    "gn:asciiname":"Nawaqabena",
    "gn:country_code":"FJ",
    "gn:dem":62,
    "gn:feature_class":"P",
    "gn:feature_code":"PPL",
    "gn:name":"Nawaqabena",
    "gn:population":0,
    "gn:timezone":"Pacific/Fiji",
    "iso:country":"FJ",
    "name:fij_x_preferred":[
        "Nawaqabena"
    ],
    "name:und_x_variant":[
        "Nawanggabena",
        "Nawanggambena"
    ],
    "wof:name":"Nawaqabena",
    "wof:placetype":"locality"
},
  "geometry": {"coordinates":[178.37132,-17.93642000000001],"type":"Point"}
}