{
  "type": "Feature",
  "properties": {
    "gn:admin1_code":"05",
    "gn:admin2_code":"2198946",
    "gn:asciiname":"Nauria",
    "gn:country_code":"FJ",
    "gn:dem":128,
    "gn:feature_class":"P",
    "gn:feature_code":"PPL",
    "gn:name":"Nauria",
    "gn:population":0,
    "gn:timezone":"Pacific/Fiji",
    "iso:country":"FJ",
    "name:und_x_variant":[
        "Naurea",
        "Nauria"
    ],
    "wof:name":"Nauria",
    "wof:placetype":"locality"
},
  "geometry": {"coordinates":[178.13883999999999,-17.59994],"type":"Point"}
}