{
  "type": "Feature",
  "properties": {
    "gn:admin1_code":"02",
    "gn:admin2_code":"2204318",
    "gn:asciiname":"Waisomo Settlement",
    "gn:country_code":"FJ",
    "gn:dem":11,
    "gn:feature_class":"P",
    "gn:feature_code":"PPL",
    "gn:name":"Waisomo Settlement",
    "gn:population":0,
    "gn:timezone":"Pacific/Fiji",
    "iso:country":"FJ",
    "name:fij_x_preferred":[
        "Waisomo Settlement"
    ],
    "wof:name":"Waisomo Settlement",
    "wof:placetype":"locality"
},
  "geometry": {"coordinates":[179.35001,-18.04433],"type":"Point"}
}