{
  "type": "Feature",
  "properties": {
    "gn:admin1_code":"03",
    "gn:admin2_code":"2197820",
    "gn:asciiname":"Naboutini",
    "gn:country_code":"FJ",
    "gn:dem":4,
    "gn:feature_class":"P",
    "gn:feature_code":"PPL",
    "gn:name":"Naboutini",
    "gn:population":0,
    "gn:timezone":"Pacific/Fiji",
    "iso:country":"FJ",
    "name:fij_x_preferred":[
        "Naboutini"
    ],
    "name:und_x_variant":[
        "Mboutini",
        "Namboutini"
    ],
    "wof:name":"Naboutini",
    "wof:placetype":"locality"
},
  "geometry": {"coordinates":[179.81218000000001,-16.33157000000001],"type":"Point"}
}