{
  "type": "Feature",
  "properties": {
    "gn:admin1_code":"01",
    "gn:admin2_code":"2198131",
    "gn:asciiname":"Nakalawaca",
    "gn:country_code":"FJ",
    "gn:dem":21,
    "gn:feature_class":"P",
    "gn:feature_code":"PPL",
    "gn:name":"Nakalawaca",
    "gn:population":0,
    "gn:timezone":"Pacific/Fiji",
    "iso:country":"FJ",
    "name:fij_x_preferred":[
        "Nakalawaca"
    ],
    "name:und_x_variant":[
        "Nakalawatha",
        "Nakalavatha"
    ],
    "wof:name":"Nakalawaca",
    "wof:placetype":"locality"
},
  "geometry": {"coordinates":[178.5532,-17.83314],"type":"Point"}
}