{
  "type": "Feature",
  "properties": {
    "gn:admin1_code":"1.0",
    "gn:admin2_code":"2203150.0",
    "gn:asciiname":"Taulevu",
    "gn:country_code":"FJ",
    "gn:dem":135,
    "gn:feature_class":"P",
    "gn:feature_code":"PPL",
    "gn:name":"Taulevu",
    "gn:population":0,
    "gn:timezone":"Pacific/Fiji",
    "iso:country":"FJ",
    "name:fij_x_preferred":[
        "Taulevu"
    ],
    "wof:name":"Taulevu",
    "wof:placetype":"locality"
},
  "geometry": {"coordinates":[178.29372000000001,-17.8267],"type":"Point"}
}