{
  "type": "Feature",
  "properties": {
    "gn:admin1_code":"01",
    "gn:admin2_code":"2198131",
    "gn:asciiname":"Nabouciwa",
    "gn:country_code":"FJ",
    "gn:dem":2,
    "gn:feature_class":"P",
    "gn:feature_code":"PPL",
    "gn:name":"Nabouciwa",
    "gn:population":0,
    "gn:timezone":"Pacific/Fiji",
    "iso:country":"FJ",
    "name:fij_x_preferred":[
        "Nabouciwa"
    ],
    "name:und_x_variant":[
        "Nambothiwa",
        "Nambouthiwa"
    ],
    "wof:name":"Nabouciwa",
    "wof:placetype":"locality"
},
  "geometry": {"coordinates":[178.62143999999995,-18.06011],"type":"Point"}
}