{
  "type": "Feature",
  "properties": {
    "gn:admin1_code":"05",
    "gn:admin2_code":"2201984",
    "gn:asciiname":"Vuniwai Settlement",
    "gn:country_code":"FJ",
    "gn:dem":23,
    "gn:feature_class":"P",
    "gn:feature_code":"PPL",
    "gn:name":"Vuniwai Settlement",
    "gn:population":0,
    "gn:timezone":"Pacific/Fiji",
    "iso:country":"FJ",
    "name:fij_x_preferred":[
        "Vuniwai Settlement"
    ],
    "wof:name":"Vuniwai Settlement",
    "wof:placetype":"locality"
},
  "geometry": {"coordinates":[177.72976,-18.2116],"type":"Point"}
}