{
  "type": "Feature",
  "properties": {
    "gn:admin1_code":"03",
    "gn:asciiname":"Mbouma",
    "gn:cc2":"FJ",
    "gn:country_code":"FJ",
    "gn:dem":5,
    "gn:feature_class":"P",
    "gn:feature_code":"PPL",
    "gn:name":"Mbouma",
    "gn:population":0,
    "gn:timezone":"Pacific/Fiji",
    "iso:country":"FJ",
    "name:fij_x_preferred":[
        "Bouma"
    ],
    "name:und_x_variant":[
        "Mboumba",
        "Mbuma",
        "Mboma",
        "Mbouma"
    ],
    "wof:name":"Mbouma",
    "wof:placetype":"locality"
},
  "geometry": {"coordinates":[-179.87091000000001,-16.82262],"type":"Point"}
}