{
  "type": "Feature",
  "properties": {
    "gn:admin1_code":"01",
    "gn:admin2_code":"2198876",
    "gn:asciiname":"Laucala",
    "gn:country_code":"FJ",
    "gn:dem":6,
    "gn:feature_class":"P",
    "gn:feature_code":"PPL",
    "gn:name":"Laucala",
    "gn:population":0,
    "gn:timezone":"Pacific/Fiji",
    "iso:country":"FJ",
    "name:ara_x_preferred":[
        "\u0644\u0627\u0648\u0643\u0627\u0644\u0627"
    ],
    "name:ceb_x_preferred":[
        "Laucala Island"
    ],
    "name:ces_x_preferred":[
        "Laucala"
    ],
    "name:deu_x_preferred":[
        "Laucala"
    ],
    "name:fij_x_preferred":[
        "Laucala"
    ],
    "name:hif_x_preferred":[
        "Laucala"
    ],
    "name:ita_x_preferred":[
        "Laucala"
    ],
    "name:nld_x_preferred":[
        "Laucala"
    ],
    "name:rus_x_preferred":[
        "\u041b\u0430\u0443\u0442\u0430\u043b\u0430"
    ],
    "name:swe_x_preferred":[
        "Laucala"
    ],
    "name:und_x_variant":[
        "Lauthala"
    ],
    "name:urd_x_preferred":[
        "\u0644\u0648\u06a9\u0627\u0644\u0627"
    ],
    "wof:name":"Laucala",
    "wof:placetype":"locality"
},
  "geometry": {"coordinates":[178.51445000000001,-18.14652],"type":"Point"}
}