{
  "type": "Feature",
  "properties": {
    "gn:admin1_code":"01",
    "gn:admin2_code":"2198876",
    "gn:asciiname":"Muanaicake Settlement",
    "gn:country_code":"FJ",
    "gn:dem":7,
    "gn:feature_class":"P",
    "gn:feature_code":"PPL",
    "gn:name":"Muanaicake Settlement",
    "gn:population":0,
    "gn:timezone":"Pacific/Fiji",
    "iso:country":"FJ",
    "name:fij_x_preferred":[
        "Muanaicake Settlement"
    ],
    "wof:name":"Muanaicake Settlement",
    "wof:placetype":"locality"
},
  "geometry": {"coordinates":[178.36717999999999,-18.12118],"type":"Point"}
}