{
  "type": "Feature",
  "properties": {
    "gn:admin1_code":"05",
    "gn:admin2_code":"2198946",
    "gn:asciiname":"Naivaka Settlement",
    "gn:country_code":"FJ",
    "gn:dem":140,
    "gn:feature_class":"P",
    "gn:feature_code":"PPL",
    "gn:name":"Naivaka Settlement",
    "gn:population":0,
    "gn:timezone":"Pacific/Fiji",
    "iso:country":"FJ",
    "name:fij_x_preferred":[
        "Naivaka Settlement"
    ],
    "wof:name":"Naivaka Settlement",
    "wof:placetype":"locality"
},
  "geometry": {"coordinates":[178.12458999999996,-17.59058],"type":"Point"}
}