{
  "type": "Feature",
  "properties": {
    "gn:admin1_code":"01",
    "gn:admin2_code":"2203150",
    "gn:asciiname":"Waimalua Settlement",
    "gn:country_code":"FJ",
    "gn:dem":42,
    "gn:feature_class":"P",
    "gn:feature_code":"PPL",
    "gn:name":"Waimalua Settlement",
    "gn:population":0,
    "gn:timezone":"Pacific/Fiji",
    "iso:country":"FJ",
    "name:fij_x_preferred":[
        "Waimalua Settlement"
    ],
    "wof:name":"Waimalua Settlement",
    "wof:placetype":"locality"
},
  "geometry": {"coordinates":[178.28428,-17.85288],"type":"Point"}
}