{
  "type": "Feature",
  "properties": {
    "gn:admin1_code":"00",
    "gn:asciiname":"Koromathi",
    "gn:cc2":"FJ",
    "gn:country_code":"FJ",
    "gn:dem":109,
    "gn:feature_class":"P",
    "gn:feature_code":"PPL",
    "gn:name":"Koromathi",
    "gn:population":0,
    "gn:timezone":"Pacific/Fiji",
    "iso:country":"FJ",
    "name:und_x_variant":[
        "Karomaci",
        "Koromathi"
    ],
    "wof:name":"Koromathi",
    "wof:placetype":"locality"
},
  "geometry": {"coordinates":[179.76667,-19.13333],"type":"Point"}
}