{
  "type": "Feature",
  "properties": {
    "gn:admin1_code":"05",
    "gn:admin2_code":"2201984",
    "gn:asciiname":"Nasautabu",
    "gn:country_code":"FJ",
    "gn:dem":44,
    "gn:feature_class":"P",
    "gn:feature_code":"PPL",
    "gn:name":"Nasautabu",
    "gn:population":0,
    "gn:timezone":"Pacific/Fiji",
    "iso:country":"FJ",
    "name:fij_x_preferred":[
        "Nasautabu"
    ],
    "wof:name":"Nasautabu",
    "wof:placetype":"locality"
},
  "geometry": {"coordinates":[177.63449,-17.9682],"type":"Point"}
}