{
  "type": "Feature",
  "properties": {
    "gn:admin1_code":"1.0",
    "gn:admin2_code":"2203150.0",
    "gn:asciiname":"Tovutovu Settlement",
    "gn:country_code":"FJ",
    "gn:dem":19,
    "gn:feature_class":"P",
    "gn:feature_code":"PPL",
    "gn:name":"Tovutovu Settlement",
    "gn:population":0,
    "gn:timezone":"Pacific/Fiji",
    "iso:country":"FJ",
    "name:fij_x_preferred":[
        "Tovutovu Settlement"
    ],
    "name:fij_x_variant":[
        "Tovutovu"
    ],
    "wof:name":"Tovutovu Settlement",
    "wof:placetype":"locality"
},
  "geometry": {"coordinates":[178.43608,-17.96561],"type":"Point"}
}