{
  "type": "Feature",
  "properties": {
    "gn:admin1_code":"05",
    "gn:admin2_code":"2201984",
    "gn:asciiname":"Nagasau Settlement",
    "gn:country_code":"FJ",
    "gn:dem":11,
    "gn:feature_class":"P",
    "gn:feature_code":"PPL",
    "gn:name":"Nagasau Settlement",
    "gn:population":0,
    "gn:timezone":"Pacific/Fiji",
    "iso:country":"FJ",
    "name:fij_x_preferred":[
        "Nagasau Settlement"
    ],
    "wof:name":"Nagasau Settlement",
    "wof:placetype":"locality"
},
  "geometry": {"coordinates":[177.67644000000001,-18.20304],"type":"Point"}
}