{
  "type": "Feature",
  "properties": {
    "gn:admin1_code":"05",
    "gn:admin2_code":"2201984",
    "gn:asciiname":"Nalili Settlement",
    "gn:country_code":"FJ",
    "gn:dem":291,
    "gn:feature_class":"P",
    "gn:feature_code":"PPL",
    "gn:name":"Nalili Settlement",
    "gn:population":0,
    "gn:timezone":"Pacific/Fiji",
    "iso:country":"FJ",
    "name:fij_x_preferred":[
        "Nalili Settlement"
    ],
    "wof:name":"Nalili Settlement",
    "wof:placetype":"locality"
},
  "geometry": {"coordinates":[177.83961000000005,-17.87164],"type":"Point"}
}