{
  "type": "Feature",
  "properties": {
    "gn:admin1_code":"04",
    "gn:asciiname":"Haroa",
    "gn:country_code":"FJ",
    "gn:dem":7,
    "gn:feature_class":"P",
    "gn:feature_code":"PPL",
    "gn:name":"Haroa",
    "gn:population":0,
    "gn:timezone":"Pacific/Fiji",
    "iso:country":"FJ",
    "name:fij_x_preferred":[
        "Haroa"
    ],
    "wof:name":"Haroa",
    "wof:placetype":"locality"
},
  "geometry": {"coordinates":[177.03649999999999,-12.50877],"type":"Point"}
}